Workbook

Sheet Sheet3
B3: New | E3: Market growth new cars | J3: 35
J4: 0.35
E5: RAR | J5: =J4*J3 -> 12.25
E6: Cars financed | J6: =(J5*1000)/#REF! -> #REF!
B7: B2B opportunity | E7: RAR | F7: €M | J7: =3*50% -> 1.5 | K7: =50%*4 -> 2 | M7: 50% new and 50 % used | T7: 3 | U7: 4
C8: New | E8: Cars financed | F8: €M | J8: =J7*1000/#REF! -> #REF! | K8: =K7*1000/#REF! -> #REF!
C9: Used | E9: RAR | F9: €M | J9: =3*50% -> 1.5 | K9: =50%*4 -> 2
C10: Used | E10: Cars financed | F10: €M | J10: =J9*1000/#REF! -> #REF! | K10: =K9*1000/#REF! -> #REF!
B12: D2C | C12: Total | D12: Cash loan | E12: RAR | F12: €M | J12: 2 | K12: 3
C13: New | D13: Cash loan | E13: RAR | F13: €M | J13: =15%*J12 -> 0.3 | K13: =15%*K12 -> 0.45
B14: D2C | C14: New | D14: Cash loan | E14: cars financed | F14: k# | J14: =J13*1000/#REF! -> #REF! | K14: =K13*1000/#REF! -> #REF! | M14: B2C cars
M15: B2C is new
B16: Toyota | C16: Total | D16: Auto loan | E16: RAR | F16: €M | J16: 1 | K16: 2
C17: New | D17: Auto loan | E17: RAR | F17: €M | J17: =70%*J16 -> 0.7 | K17: =70%*K16 -> 1.4
C18: New | D18: Auto loan | E18: cars financed | F18: k# | J18: =J17*1000/#REF! -> #REF! | K18: =J17*1000/#REF! -> #REF!
C19: Used | D19: Auto loan | E19: RAR | F19: €M | J19: =J16-J17 -> 0.3 | K19: =K16-K17 -> 0.6
C20: Used | D20: Auto loan | E20: cars financed | F20: k# | J20: =J19*1000/#REF! -> #REF! | K20: =K19*1000/#REF! -> #REF!
B22: Used car finacing | E22: cars financed | F22: k# | J22: =#REF! -> #REF! | K22: =J22 -> #REF!
B24: Digital presence (Car.gr + Cardom) | E24: RAR | F24: €M | J24: =#REF!+#REF! -> #REF! | K24: =#REF!+#REF! -> #REF!
E25: cars financed | F25: k# | J25: =J24*1000/#REF! -> #REF! | K25: =K24*1000/#REF! -> #REF!
B27: Total | C27: New | J27: =J6+J8+J17 -> #REF! | K27: =J6+K8+K17 -> #REF! | M27: C2C is used
C28: Used | J28: =J25+J22+J20+J10 -> #REF! | K28: =K25+K22+K20+K10 -> #REF!

Sheet Business case on loan
K1: =+K9/K6 -> 0.41297664 | L1: =+L9/L6 -> 0.37109671 | M1: =+M9/M6 -> 0.38099352 | N1: =+N9/N6 -> 0.3684306
K2: =+K10/K7 -> 0.1497678 | L2: =+L10/L7 -> 0.13653813 | M2: =+M10/M7 -> 0.24747783 | N2: =+N10/N7 -> 0.24162759
D3: Total BP
D4: KPI | K4: 2024 | L4: =K4+1 -> 2025 | M4: =L4+1 -> 2026 | N4: =M4+1 -> 2027 | O4: =N4+1 -> 2028 | P4: =O4+1 -> 2029 | Q4: =P4+1 -> 2030 | S4: Notes
Q5: Min | R5: Max
D6: Cars financed | E6: Market | F6: New | G6: Auto loan | J6: k# | K6: =(K13*10^6/K182)/1000 -> 24.666667 | L6: =(L13*10^6/L182)/1000 -> 27.274085 | M6: =(M13*10^6/M182)/1000 -> 29.749722 | N6: =(N13*10^6/N182)/1000 -> 32.103322 | O6: =(O13*10^6/O182)/1000 -> 34.343692 | P6: =(P13*10^6/P182)/1000 -> 36.478812 | Q6: =(Q13*10^6/Q182)/1000 -> 38.515927 | R6: =(R13*10^6/R182)/1000 -> 38.515927
D7: Cars financed | E7: Market | F7: Used | G7: Auto loan | J7: k# | K7: =(K14*10^6/K183)/1000 -> 21.052632 | L7: =(L14*10^6/L183)/1000 -> 23.411965 | M7: =(M14*10^6/M183)/1000 -> 25.652056 | N7: =(N14*10^6/N183)/1000 -> 27.781721 | O7: =(O14*10^6/O183)/1000 -> 29.80893 | P7: =(P14*10^6/P183)/1000 -> 31.740901 | Q7: =(Q14*10^6/Q183)/1000 -> 33.584194 | R7: =(R14*10^6/R183)/1000 -> 33.584194
D8: Cars financed | E8: Market | F8: Used | G8: Cash loan | J8: k# | K8: =(K15*10^6/K184)/1000 -> 24 | L8: =(L15*10^6/L184)/1000 -> 24.351861 | M8: =(M15*10^6/M184)/1000 -> 24.685939 | N8: =(N15*10^6/N184)/1000 -> 25.003549 | O8: =(O15*10^6/O184)/1000 -> 25.305879 | P8: =(P15*10^6/P184)/1000 -> 25.594005 | Q8: =(Q15*10^6/Q184)/1000 -> 25.868906 | R8: =(R15*10^6/R184)/1000 -> 25.868906
D9: Cars financed | E9: Eurobank | F9: New | G9: Auto loan | J9: k# | K9: 10.186757 | L9: =SUMIFS(L$41:L$88,$G$41:$G$88,$G9,$F$41:$F$88,$F9,$D$41:$D$88,$D9) -> 10.121323 | M9: =SUMIFS(M$41:M$88,$G$41:$G$88,$G9,$F$41:$F$88,$F9,$D$41:$D$88,$D9) -> 11.334451 | N9: =SUMIFS(N$41:N$88,$G$41:$G$88,$G9,$F$41:$F$88,$F9,$D$41:$D$88,$D9) -> 11.827846 | O9: =SUMIFS(O$41:O$88,$G$41:$G$88,$G9,$F$41:$F$88,$F9,$D$41:$D$88,$D9) -> 12.008141 | P9: =SUMIFS(P$41:P$88,$G$41:$G$88,$G9,$F$41:$F$88,$F9,$D$41:$D$88,$D9) -> 12.191568 | Q9: =SUMIFS(Q$41:Q$88,$G$41:$G$88,$G9,$F$41:$F$88,$F9,$D$41:$D$88,$D9) -> 12.6897 | R9: =SUMIFS(R$41:R$88,$G$41:$G$88,$G9,$F$41:$F$88,$F9,$D$41:$D$88,$D9) -> 13.40725
D10: Cars financed | E10: Eurobank | F10: Used | G10: Auto loan | J10: k# | K10: 3.1530064 | L10: =SUMIFS(L$41:L$88,$G$41:$G$88,$G10,$F$41:$F$88,$F10,$D$41:$D$88,$D10) -> 3.1966259 | M10: =SUMIFS(M$41:M$88,$G$41:$G$88,$G10,$F$41:$F$88,$F10,$D$41:$D$88,$D10) -> 6.3483151 | N10: =SUMIFS(N$41:N$88,$G$41:$G$88,$G10,$F$41:$F$88,$F10,$D$41:$D$88,$D10) -> 6.7128304 | O10: =SUMIFS(O$41:O$88,$G$41:$G$88,$G10,$F$41:$F$88,$F10,$D$41:$D$88,$D10) -> 9.1555174 | P10: =SUMIFS(P$41:P$88,$G$41:$G$88,$G10,$F$41:$F$88,$F10,$D$41:$D$88,$D10) -> 9.6804039 | Q10: =SUMIFS(Q$41:Q$88,$G$41:$G$88,$G10,$F$41:$F$88,$F10,$D$41:$D$88,$D10) -> 10.87049 | R10: =SUMIFS(R$41:R$88,$G$41:$G$88,$G10,$F$41:$F$88,$F10,$D$41:$D$88,$D10) -> 11.782047
D11: Cars financed | E11: Eurobank | F11: Used | G11: Cash loan | J11: k# | K11: 7 | L11: =SUMIFS(L$41:L$88,$G$41:$G$88,$G11,$F$41:$F$88,$F11,$D$41:$D$88,$D11) -> 7.3055584 | M11: =SUMIFS(M$41:M$88,$G$41:$G$88,$G11,$F$41:$F$88,$F11,$D$41:$D$88,$D11) -> 7.6191151 | N11: =SUMIFS(N$41:N$88,$G$41:$G$88,$G11,$F$41:$F$88,$F11,$D$41:$D$88,$D11) -> 8.2298867 | O11: =SUMIFS(O$41:O$88,$G$41:$G$88,$G11,$F$41:$F$88,$F11,$D$41:$D$88,$D11) -> 8.8440396 | P11: =SUMIFS(P$41:P$88,$G$41:$G$88,$G11,$F$41:$F$88,$F11,$D$41:$D$88,$D11) -> 9.4618054 | Q11: =SUMIFS(Q$41:Q$88,$G$41:$G$88,$G11,$F$41:$F$88,$F11,$D$41:$D$88,$D11) -> 9.8536909 | R11: =SUMIFS(R$41:R$88,$G$41:$G$88,$G11,$F$41:$F$88,$F11,$D$41:$D$88,$D11) -> 11.21134
D12: Cars financed | E12: Eurobank | F12: Total | G12: Total | J12: k# | K12: =SUM(K9:K11) -> 20.339764 | L12: =SUM(L9:L11) -> 20.623507 | M12: =SUM(M9:M11) -> 25.301882 | N12: =SUM(N9:N11) -> 26.770563 | O12: =SUM(O9:O11) -> 30.007698 | P12: =SUM(P9:P11) -> 31.333778 | Q12: =SUM(Q9:Q11) -> 33.41388 | R12: =SUM(R9:R11) -> 36.400637
D13: Loan disbursements | E13: Market | F13: New | G13: Auto loan | J13: €M | K13: 370 | L13: =K13+($R13-$K13)/($Q$41-$K$41) -> 420 | M13: =L13+($R13-$K13)/($Q$41-$K$41) -> 470 | N13: =M13+($R13-$K13)/($Q$41-$K$41) -> 520 | O13: =N13+($R13-$K13)/($Q$41-$K$41) -> 570 | P13: =O13+($R13-$K13)/($Q$41-$K$41) -> 620 | Q13: =P13+($R13-$K13)/($Q$41-$K$41) -> 670 | R13: 670
D14: Loan disbursements | E14: Market | F14: Used | G14: Auto loan | J14: €M | K14: 200 | L14: =K14+($R14-$K14)/($Q$41-$K$41) -> 228.33333 | M14: =L14+($R14-$K14)/($Q$41-$K$41) -> 256.66667 | N14: =M14+($R14-$K14)/($Q$41-$K$41) -> 285 | O14: =N14+($R14-$K14)/($Q$41-$K$41) -> 313.33333 | P14: =O14+($R14-$K14)/($Q$41-$K$41) -> 341.66667 | Q14: =P14+($R14-$K14)/($Q$41-$K$41) -> 370 | R14: 370
D15: Loan disbursements | E15: Market | F15: Used | G15: Cash loan | J15: €M | K15: 120 | L15: =K15+($R15-$K15)/($Q$41-$K$41) -> 125 | M15: =L15+($R15-$K15)/($Q$41-$K$41) -> 130 | N15: =M15+($R15-$K15)/($Q$41-$K$41) -> 135 | O15: =N15+($R15-$K15)/($Q$41-$K$41) -> 140 | P15: =O15+($R15-$K15)/($Q$41-$K$41) -> 145 | Q15: =P15+($R15-$K15)/($Q$41-$K$41) -> 150 | R15: 150
D16: Loan disbursements | E16: Eurobank | F16: New | G16: Auto loan | J16: €M | K16: =SUMIFS(K$41:K$88,$G$41:$G$88,$G16,$F$41:$F$88,$F16,$D$41:$D$88,$D16) -> 152.80136 | L16: =SUMIFS(L$41:L$88,$G$41:$G$88,$G16,$F$41:$F$88,$F16,$D$41:$D$88,$D16) -> 155.83831 | M16: =SUMIFS(M$41:M$88,$G$41:$G$88,$G16,$F$41:$F$88,$F16,$D$41:$D$88,$D16) -> 179.01846 | N16: =SUMIFS(N$41:N$88,$G$41:$G$88,$G16,$F$41:$F$88,$F16,$D$41:$D$88,$D16) -> 191.50564 | O16: =SUMIFS(O$41:O$88,$G$41:$G$88,$G16,$F$41:$F$88,$F16,$D$41:$D$88,$D16) -> 199.18696 | P16: =SUMIFS(P$41:P$88,$G$41:$G$88,$G16,$F$41:$F$88,$F16,$D$41:$D$88,$D16) -> 207.06242 | Q16: =SUMIFS(Q$41:Q$88,$G$41:$G$88,$G16,$F$41:$F$88,$F16,$D$41:$D$88,$D16) -> 220.55587 | R16: =SUMIFS(R$41:R$88,$G$41:$G$88,$G16,$F$41:$F$88,$F16,$D$41:$D$88,$D16) -> 233.2245
D17: Loan disbursements | E17: Eurobank | F17: Used | G17: Auto loan | J17: €M | K17: =SUMIFS(K$41:K$88,$G$41:$G$88,$G17,$F$41:$F$88,$F17,$D$41:$D$88,$D17) -> 29.95356 | L17: =SUMIFS(L$41:L$88,$G$41:$G$88,$G17,$F$41:$F$88,$F17,$D$41:$D$88,$D17) -> 31.13316 | M17: =SUMIFS(M$41:M$88,$G$41:$G$88,$G17,$F$41:$F$88,$F17,$D$41:$D$88,$D17) -> 63.43246 | N17: =SUMIFS(N$41:N$88,$G$41:$G$88,$G17,$F$41:$F$88,$F17,$D$41:$D$88,$D17) -> 68.73251 | O17: =SUMIFS(O$41:O$88,$G$41:$G$88,$G17,$F$41:$F$88,$F17,$D$41:$D$88,$D17) -> 96.060723 | P17: =SUMIFS(P$41:P$88,$G$41:$G$88,$G17,$F$41:$F$88,$F17,$D$41:$D$88,$D17) -> 103.97993 | Q17: =SUMIFS(Q$41:Q$88,$G$41:$G$88,$G17,$F$41:$F$88,$F17,$D$41:$D$88,$D17) -> 119.49256 | R17: =SUMIFS(R$41:R$88,$G$41:$G$88,$G17,$F$41:$F$88,$F17,$D$41:$D$88,$D17) -> 129.57171
D18: Loan disbursements | E18: Eurobank | F18: Used | G18: Cash loan | J18: €M | K18: =SUMIFS(K$41:K$88,$G$41:$G$88,$G18,$F$41:$F$88,$F18,$D$41:$D$88,$D18) -> 37 | L18: =SUMIFS(L$41:L$88,$G$41:$G$88,$G18,$F$41:$F$88,$F18,$D$41:$D$88,$D18) -> 37.5 | M18: =SUMIFS(M$41:M$88,$G$41:$G$88,$G18,$F$41:$F$88,$F18,$D$41:$D$88,$D18) -> 40.123447 | N18: =SUMIFS(N$41:N$88,$G$41:$G$88,$G18,$F$41:$F$88,$F18,$D$41:$D$88,$D18) -> 44.43508 | O18: =SUMIFS(O$41:O$88,$G$41:$G$88,$G18,$F$41:$F$88,$F18,$D$41:$D$88,$D18) -> 48.927981 | P18: =SUMIFS(P$41:P$88,$G$41:$G$88,$G18,$F$41:$F$88,$F18,$D$41:$D$88,$D18) -> 53.60481 | Q18: =SUMIFS(Q$41:Q$88,$G$41:$G$88,$G18,$F$41:$F$88,$F18,$D$41:$D$88,$D18) -> 56.351367 | R18: =SUMIFS(R$41:R$88,$G$41:$G$88,$G18,$F$41:$F$88,$F18,$D$41:$D$88,$D18) -> 64.223654
D19: Loan disbursements | E19: Eurobank | F19: Total | G19: Total | J19: €M | K19: =SUM(K16:K18) -> 219.75492 | L19: =SUM(L16:L18) -> 224.47147 | M19: =SUM(M16:M18) -> 282.57436 | N19: =SUM(N16:N18) -> 304.67323 | O19: =SUM(O16:O18) -> 344.17567 | P19: =SUM(P16:P18) -> 364.64715 | Q19: =SUM(Q16:Q18) -> 396.3998 | R19: =SUM(R16:R18) -> 427.01986
D20: Market share | E20: Eurobank | F20: New | G20: Auto loan | J20: % | K20: =K16/K13 -> 0.41297664 | L20: =L16/L13 -> 0.37104359 | M20: =M16/M13 -> 0.38089033 | N20: =N16/N13 -> 0.36828008 | O20: =O16/O13 -> 0.34945081 | P20: =P16/P13 -> 0.33397164 | Q20: =Q16/Q13 -> 0.32918787 | R20: =R16/R13 -> 0.34809627
D21: Market share | E21: Eurobank | F21: Used | G21: Auto loan | J21: % | K21: =K17/K14 -> 0.1497678 | L21: =L17/L14 -> 0.1363496 | M21: =M17/M14 -> 0.24713945 | N21: =N17/N14 -> 0.2411667 | O21: =O17/O14 -> 0.30657678 | P21: =P17/P14 -> 0.30433149 | Q21: =Q17/Q14 -> 0.32295287 | R21: =R17/R14 -> 0.35019382
D22: Market share | E22: Eurobank | F22: Used | G22: Cash loan | J22: % | K22: =K18/K15 -> 0.30833333 | L22: =L18/L15 -> 0.3 | M22: =M18/M15 -> 0.3086419 | N22: =N18/N15 -> 0.32914874 | O22: =O18/O15 -> 0.34948558 | P22: =P18/P15 -> 0.36968835 | Q22: =Q18/Q15 -> 0.37567578 | R22: =R18/R15 -> 0.42815769
D23: Market share | E23: Eurobank | F23: Total | J23: % | K23: 0.3 | L23: 0.3 | M23: 0.32985334 | N23: 0.32412046 | O23: 0.33 | P23: 0.32950044 | Q23: 0.33310908 | R23: 0.35884022
D24: RAR | E24: Eurobank | F24: New | G24: Auto loan | J24: €M | K24: =SUMIFS(K$41:K$88,$G$41:$G$88,$G24,$F$41:$F$88,$F24,$D$41:$D$88,$D24) -> 10 | L24: =SUMIFS(L$41:L$88,$G$41:$G$88,$G24,$F$41:$F$88,$F24,$D$41:$D$88,$D24) -> 10.198751 | M24: =SUMIFS(M$41:M$88,$G$41:$G$88,$G24,$F$41:$F$88,$F24,$D$41:$D$88,$D24) -> 11.715763 | N24: =SUMIFS(N$41:N$88,$G$41:$G$88,$G24,$F$41:$F$88,$F24,$D$41:$D$88,$D24) -> 12.53298 | O24: =SUMIFS(O$41:O$88,$G$41:$G$88,$G24,$F$41:$F$88,$F24,$D$41:$D$88,$D24) -> 13.03568 | P24: =SUMIFS(P$41:P$88,$G$41:$G$88,$G24,$F$41:$F$88,$F24,$D$41:$D$88,$D24) -> 13.551085 | Q24: =SUMIFS(Q$41:Q$88,$G$41:$G$88,$G24,$F$41:$F$88,$F24,$D$41:$D$88,$D24) -> 14.434157 | R24: =SUMIFS(R$41:R$88,$G$41:$G$88,$G24,$F$41:$F$88,$F24,$D$41:$D$88,$D24) -> 15.263248
D25: RAR | E25: Eurobank | F25: Used | G25: Auto loan | J25: €M | K25: =SUMIFS(K$41:K$88,$G$41:$G$88,$G25,$F$41:$F$88,$F25,$D$41:$D$88,$D25) -> 4.3 | L25: =SUMIFS(L$41:L$88,$G$41:$G$88,$G25,$F$41:$F$88,$F25,$D$41:$D$88,$D25) -> 4.583785 | M25: =SUMIFS(M$41:M$88,$G$41:$G$88,$G25,$F$41:$F$88,$F25,$D$41:$D$88,$D25) -> 8.6617233 | N25: =SUMIFS(N$41:N$88,$G$41:$G$88,$G25,$F$41:$F$88,$F25,$D$41:$D$88,$D25) -> 9.4117305 | O25: =SUMIFS(O$41:O$88,$G$41:$G$88,$G25,$F$41:$F$88,$F25,$D$41:$D$88,$D25) -> 13.29418 | P25: =SUMIFS(P$41:P$88,$G$41:$G$88,$G25,$F$41:$F$88,$F25,$D$41:$D$88,$D25) -> 14.357454 | Q25: =SUMIFS(Q$41:Q$88,$G$41:$G$88,$G25,$F$41:$F$88,$F25,$D$41:$D$88,$D25) -> 16.289561 | R25: =SUMIFS(R$41:R$88,$G$41:$G$88,$G25,$F$41:$F$88,$F25,$D$41:$D$88,$D25) -> 17.589585
D26: RAR | E26: Eurobank | F26: Used | G26: Cash loan | J26: €M | K26: =SUMIFS(K$41:K$88,$G$41:$G$88,$G26,$F$41:$F$88,$F26,$D$41:$D$88,$D26) -> 5 | L26: =SUMIFS(L$41:L$88,$G$41:$G$88,$G26,$F$41:$F$88,$F26,$D$41:$D$88,$D26) -> 5.3833333 | M26: =SUMIFS(M$41:M$88,$G$41:$G$88,$G26,$F$41:$F$88,$F26,$D$41:$D$88,$D26) -> 5.7262403 | N26: =SUMIFS(N$41:N$88,$G$41:$G$88,$G26,$F$41:$F$88,$F26,$D$41:$D$88,$D26) -> 6.3254502 | O26: =SUMIFS(O$41:O$88,$G$41:$G$88,$G26,$F$41:$F$88,$F26,$D$41:$D$88,$D26) -> 6.9486441 | P26: =SUMIFS(P$41:P$88,$G$41:$G$88,$G26,$F$41:$F$88,$F26,$D$41:$D$88,$D26) -> 7.596124 | Q26: =SUMIFS(Q$41:Q$88,$G$41:$G$88,$G26,$F$41:$F$88,$F26,$D$41:$D$88,$D26) -> 8.0769867 | R26: =SUMIFS(R$41:R$88,$G$41:$G$88,$G26,$F$41:$F$88,$F26,$D$41:$D$88,$D26) -> 9.1862227
D27: RAR | E27: Eurobank | F27: Total | G27: Total | J27: €M | K27: =SUM(K24:K26) -> 19.3 | L27: =SUM(L24:L26) -> 20.16587 | M27: =SUM(M24:M26) -> 26.103727 | N27: =SUM(N24:N26) -> 28.270161 | O27: =SUM(O24:O26) -> 33.278504 | P27: =SUM(P24:P26) -> 35.504663 | Q27: =SUM(Q24:Q26) -> 38.800705 | R27: =SUM(R24:R26) -> 42.039055
B28: Highly preliminary | D28: Opex | E28: Eurobank | F28: New | G28: Auto loan | J28: €M | K28: =SUMIFS(K$41:K$88,$G$41:$G$88,$G28,$F$41:$F$88,$F28,$D$41:$D$88,$D28) -> 2.9333286 | L28: =SUMIFS(L$41:L$88,$G$41:$G$88,$G28,$F$41:$F$88,$F28,$D$41:$D$88,$D28) -> 2.7536593 | M28: =SUMIFS(M$41:M$88,$G$41:$G$88,$G28,$F$41:$F$88,$F28,$D$41:$D$88,$D28) -> 2.8898855 | N28: =SUMIFS(N$41:N$88,$G$41:$G$88,$G28,$F$41:$F$88,$F28,$D$41:$D$88,$D28) -> 2.7990308 | O28: =SUMIFS(O$41:O$88,$G$41:$G$88,$G28,$F$41:$F$88,$F28,$D$41:$D$88,$D28) -> 2.607136 | P28: =SUMIFS(P$41:P$88,$G$41:$G$88,$G28,$F$41:$F$88,$F28,$D$41:$D$88,$D28) -> 2.7102169 | Q28: =SUMIFS(Q$41:Q$88,$G$41:$G$88,$G28,$F$41:$F$88,$F28,$D$41:$D$88,$D28) -> 2.8868313 | R28: =SUMIFS(R$41:R$88,$G$41:$G$88,$G28,$F$41:$F$88,$F28,$D$41:$D$88,$D28) -> 3.8158119 | S28: Considered 25-20% Opex/RAR, starting from 29% in 2024 (source ERB P&L) and gradually decreasing to 20% in 2030
B29: Highly preliminary | D29: Opex | E29: Eurobank | F29: Used | G29: Auto loan | J29: €M | K29: =SUMIFS(K$41:K$88,$G$41:$G$88,$G29,$F$41:$F$88,$F29,$D$41:$D$88,$D29) -> 0.602 | L29: =SUMIFS(L$41:L$88,$G$41:$G$88,$G29,$F$41:$F$88,$F29,$D$41:$D$88,$D29) -> 0.60505962 | M29: =SUMIFS(M$41:M$88,$G$41:$G$88,$G29,$F$41:$F$88,$F29,$D$41:$D$88,$D29) -> 1.0740537 | N29: =SUMIFS(N$41:N$88,$G$41:$G$88,$G29,$F$41:$F$88,$F29,$D$41:$D$88,$D29) -> 1.0917607 | O29: =SUMIFS(O$41:O$88,$G$41:$G$88,$G29,$F$41:$F$88,$F29,$D$41:$D$88,$D29) -> 1.4357714 | P29: =SUMIFS(P$41:P$88,$G$41:$G$88,$G29,$F$41:$F$88,$F29,$D$41:$D$88,$D29) -> 1.4357454 | Q29: =SUMIFS(Q$41:Q$88,$G$41:$G$88,$G29,$F$41:$F$88,$F29,$D$41:$D$88,$D29) -> 1.9547474 | R29: =SUMIFS(R$41:R$88,$G$41:$G$88,$G29,$F$41:$F$88,$F29,$D$41:$D$88,$D29) -> 2.6384377 | S29: Considered 10-15% Opex/RAR, starting from 15% in 2024 (source ERB P&L) and gradually decreasing to 12% in 2030
B30: Highly preliminary | D30: Opex | E30: Eurobank | F30: Used | G30: Cash loan | J30: €M | K30: =SUMIFS(K$41:K$88,$G$41:$G$88,$G30,$F$41:$F$88,$F30,$D$41:$D$88,$D30) -> 0.75 | L30: =SUMIFS(L$41:L$88,$G$41:$G$88,$G30,$F$41:$F$88,$F30,$D$41:$D$88,$D30) -> 0.8075 | M30: =SUMIFS(M$41:M$88,$G$41:$G$88,$G30,$F$41:$F$88,$F30,$D$41:$D$88,$D30) -> 0.85893604 | N30: =SUMIFS(N$41:N$88,$G$41:$G$88,$G30,$F$41:$F$88,$F30,$D$41:$D$88,$D30) -> 0.94881754 | O30: =SUMIFS(O$41:O$88,$G$41:$G$88,$G30,$F$41:$F$88,$F30,$D$41:$D$88,$D30) -> 1.0422966 | P30: =SUMIFS(P$41:P$88,$G$41:$G$88,$G30,$F$41:$F$88,$F30,$D$41:$D$88,$D30) -> 1.1394186 | Q30: =SUMIFS(Q$41:Q$88,$G$41:$G$88,$G30,$F$41:$F$88,$F30,$D$41:$D$88,$D30) -> 1.211548 | R30: =SUMIFS(R$41:R$88,$G$41:$G$88,$G30,$F$41:$F$88,$F30,$D$41:$D$88,$D30) -> 1.3779334 | S30: Considered 15% Opex/RAR - to be checked against cash loan incidence of Opex/ RAR
B31: Highly preliminary | D31: Opex | E31: Eurobank | F31: Total | G31: Total | J31: €M | K31: =SUM(K28:K30) -> 4.2853286 | L31: =SUM(L28:L30) -> 4.1662189 | M31: =SUM(M28:M30) -> 4.8228753 | N31: =SUM(N28:N30) -> 4.8396091 | O31: =SUM(O28:O30) -> 5.0852041 | P31: =SUM(P28:P30) -> 5.285381 | Q31: =SUM(Q28:Q30) -> 6.0531267 | R31: =SUM(R28:R30) -> 7.8321831
D32: PBT | E32: Eurobank | F32: New | G32: Auto loan | J32: €M | K32: =SUMIFS(K$41:K$88,$G$41:$G$88,$G32,$F$41:$F$88,$F32,$D$41:$D$88,$D32) -> 7.0666714 | L32: =SUMIFS(L$41:L$88,$G$41:$G$88,$G32,$F$41:$F$88,$F32,$D$41:$D$88,$D32) -> 7.4450921 | M32: =SUMIFS(M$41:M$88,$G$41:$G$88,$G32,$F$41:$F$88,$F32,$D$41:$D$88,$D32) -> 8.8258778 | N32: =SUMIFS(N$41:N$88,$G$41:$G$88,$G32,$F$41:$F$88,$F32,$D$41:$D$88,$D32) -> 9.7339495 | O32: =SUMIFS(O$41:O$88,$G$41:$G$88,$G32,$F$41:$F$88,$F32,$D$41:$D$88,$D32) -> 10.428544 | P32: =SUMIFS(P$41:P$88,$G$41:$G$88,$G32,$F$41:$F$88,$F32,$D$41:$D$88,$D32) -> 10.840868 | Q32: =SUMIFS(Q$41:Q$88,$G$41:$G$88,$G32,$F$41:$F$88,$F32,$D$41:$D$88,$D32) -> 11.547325 | R32: =SUMIFS(R$41:R$88,$G$41:$G$88,$G32,$F$41:$F$88,$F32,$D$41:$D$88,$D32) -> 11.447436
D33: PBT | E33: Eurobank | F33: Used | G33: Auto loan | J33: €M | K33: =SUMIFS(K$41:K$88,$G$41:$G$88,$G33,$F$41:$F$88,$F33,$D$41:$D$88,$D33) -> 3.698 | L33: =SUMIFS(L$41:L$88,$G$41:$G$88,$G33,$F$41:$F$88,$F33,$D$41:$D$88,$D33) -> 3.9787254 | M33: =SUMIFS(M$41:M$88,$G$41:$G$88,$G33,$F$41:$F$88,$F33,$D$41:$D$88,$D33) -> 7.5876696 | N33: =SUMIFS(N$41:N$88,$G$41:$G$88,$G33,$F$41:$F$88,$F33,$D$41:$D$88,$D33) -> 8.3199698 | O33: =SUMIFS(O$41:O$88,$G$41:$G$88,$G33,$F$41:$F$88,$F33,$D$41:$D$88,$D33) -> 11.858409 | P33: =SUMIFS(P$41:P$88,$G$41:$G$88,$G33,$F$41:$F$88,$F33,$D$41:$D$88,$D33) -> 12.921709 | Q33: =SUMIFS(Q$41:Q$88,$G$41:$G$88,$G33,$F$41:$F$88,$F33,$D$41:$D$88,$D33) -> 14.334814 | R33: =SUMIFS(R$41:R$88,$G$41:$G$88,$G33,$F$41:$F$88,$F33,$D$41:$D$88,$D33) -> 14.951147 | S33: =+R31/R27 -> 0.1863073
D34: PBT | E34: Eurobank | F34: Used | G34: Cash loan | J34: €M | K34: =SUMIFS(K$41:K$88,$G$41:$G$88,$G34,$F$41:$F$88,$F34,$D$41:$D$88,$D34) -> 4.25 | L34: =SUMIFS(L$41:L$88,$G$41:$G$88,$G34,$F$41:$F$88,$F34,$D$41:$D$88,$D34) -> 4.5758333 | M34: =SUMIFS(M$41:M$88,$G$41:$G$88,$G34,$F$41:$F$88,$F34,$D$41:$D$88,$D34) -> 4.8673042 | N34: =SUMIFS(N$41:N$88,$G$41:$G$88,$G34,$F$41:$F$88,$F34,$D$41:$D$88,$D34) -> 5.3766327 | O34: =SUMIFS(O$41:O$88,$G$41:$G$88,$G34,$F$41:$F$88,$F34,$D$41:$D$88,$D34) -> 5.9063475 | P34: =SUMIFS(P$41:P$88,$G$41:$G$88,$G34,$F$41:$F$88,$F34,$D$41:$D$88,$D34) -> 6.4567054 | Q34: =SUMIFS(Q$41:Q$88,$G$41:$G$88,$G34,$F$41:$F$88,$F34,$D$41:$D$88,$D34) -> 6.8654387 | R34: =SUMIFS(R$41:R$88,$G$41:$G$88,$G34,$F$41:$F$88,$F34,$D$41:$D$88,$D34) -> 7.8082893
D35: PBT | E35: Eurobank | F35: Total | G35: Total | J35: €M | K35: =SUM(K32:K34) -> 15.014671 | L35: =SUM(L32:L34) -> 15.999651 | M35: =SUM(M32:M34) -> 21.280852 | N35: =SUM(N32:N34) -> 23.430552 | O35: =SUM(O32:O34) -> 28.1933 | P35: =SUM(P32:P34) -> 30.219282 | Q35: =SUM(Q32:Q34) -> 32.747578 | R35: =SUM(R32:R34) -> 34.206872
D36: Capex | E36: Eurobank | F36: Total | G36: Total
L38: =+L13/K13-1 -> 0.13513514 | M38: =+M13/L13-1 -> 0.11904762 | N38: =+N13/M13-1 -> 0.10638298 | O38: =+O13/N13-1 -> 0.096153846
L39: =+(L14)/(K14)-1 -> 0.14166667 | M39: =+(M14)/(L14)-1 -> 0.12408759 | N39: =+(N14)/(M14)-1 -> 0.11038961 | O39: =+(O14)/(N14)-1 -> 0.099415205
D40: 2024 + baseline
D41: KPI | K41: 2024 | L41: =K41+1 -> 2025 | M41: =L41+1 -> 2026 | N41: =M41+1 -> 2027 | O41: =N41+1 -> 2028 | P41: =O41+1 -> 2029 | Q41: =P41+1 -> 2030 | S41: Notes
Q42: Min | R42: Max
D43: Cars financed | E43: Eurobank | F43: New | G43: Auto loan | J43: k# | K43: 10.186757 | L43: =(L47*10^6/L182)/1000 -> 10.065436 | M43: =(M47*10^6/M182)/1000 -> 10.444051 | N43: =(N47*10^6/N182)/1000 -> 10.804003 | O43: =(O47*10^6/O182)/1000 -> 10.845377 | P43: =(P47*10^6/P182)/1000 -> 10.884807 | Q43: =(Q47*10^6/Q182)/1000 -> 10.922427 | R43: =Q43 -> 10.922427 | S43: =+R43-K43 -> 0.73566975 | T43: =+S43+S44 -> 0.73566975
D44: Cars financed | E44: Eurobank | F44: Used | G44: Auto loan | J44: k# | K44: 3.1530064 | L44: 3.1530064 | M44: 3.1530064 | N44: 3.1530064 | O44: 3.1530064 | P44: 3.1530064 | Q44: 3.1530064 | R44: 3.1530064 | S44: =+R44-K44 -> 0
D45: Cars financed | E45: Eurobank | F45: Used | G45: Cash loan | J45: k# | K45: 7 | L45: =(L49*10^6/L184)/1000 -> 7.3055584 | M45: =(M49*10^6/M184)/1000 -> 7.4057818 | N45: =(N49*10^6/N184)/1000 -> 7.5010647 | O45: =(O49*10^6/O184)/1000 -> 7.5917636 | P45: =(P49*10^6/P184)/1000 -> 7.6782015 | Q45: 7.8960412 | R45: =Q45 -> 7.8960412
D46: Cars financed | E46: Eurobank | F46: Total | G46: Total | J46: k# | K46: =SUM(K43:K45) -> 20.339764 | L46: =SUM(L43:L45) -> 20.524001 | M46: =SUM(M43:M45) -> 21.002839 | N46: =SUM(N43:N45) -> 21.458074 | O46: =SUM(O43:O45) -> 21.590146 | P46: =SUM(P43:P45) -> 21.716015 | Q46: =SUM(Q43:Q45) -> 21.971475 | R46: =SUM(R43:R45) -> 21.971475
D47: Loan disbursements | E47: Eurobank | F47: New | G47: Auto loan | J47: €M | K47: 152.80136 | L47: 155 | M47: 165 | N47: 175 | O47: 180 | P47: 185 | Q47: 190 | R47: 190 | S47: =+R47-K47 -> 37.198642
D48: Loan disbursements | E48: Eurobank | F48: Used | G48: Auto loan | J48: €M | K48: 29.95356 | L48: =K48 -> 29.95356 | M48: =L48 -> 29.95356 | N48: =M48 -> 29.95356 | O48: =N48 -> 29.95356 | P48: =O48 -> 29.95356 | Q48: =P48 -> 29.95356 | R48: =Q48 -> 29.95356
D49: Loan disbursements | E49: Eurobank | F49: Used | G49: Cash loan | J49: €M | K49: 37 | L49: 37.5 | M49: 39 | N49: 40.5 | O49: 42 | P49: 43.5 | Q49: 45 | R49: 45
D50: Cars financed | E50: Eurobank | F50: Total | G50: Total | J50: k# | K50: =SUM(K47:K49) -> 219.75492 | L50: =SUM(L47:L49) -> 222.45356 | M50: =SUM(M47:M49) -> 233.95356 | N50: =SUM(N47:N49) -> 245.45356 | O50: =SUM(O47:O49) -> 251.95356 | P50: =SUM(P47:P49) -> 258.45356 | Q50: =SUM(Q47:Q49) -> 264.95356 | R50: =SUM(R47:R49) -> 264.95356
D51: RAR | E51: Eurobank | F51: New | G51: Auto loan | J51: €M | K51: 10 | L51: =L43*1000*L189/10^6 -> 10.143889 | M51: =M43*1000*M189/10^6 -> 10.798333 | N51: =N43*1000*N189/10^6 -> 11.452778 | O51: =O43*1000*O189/10^6 -> 11.78 | P51: =P43*1000*P189/10^6 -> 12.107222 | Q51: =Q43*1000*Q189/10^6 -> 12.434444 | R51: =R43*1000*R189/10^6 -> 12.434444
D52: RAR | E52: Eurobank | F52: Used | G52: Auto loan | J52: €M | K52: 4.3 | L52: =L44*1000*L190/10^6 -> 4.4144469 | M52: =M44*1000*M190/10^6 -> 4.5288939 | N52: =N44*1000*N190/10^6 -> 4.6433408 | O52: =O44*1000*O190/10^6 -> 4.7577878 | P52: =P44*1000*P190/10^6 -> 4.8722347 | Q52: =Q44*1000*Q190/10^6 -> 4.9866817 | R52: =R44*1000*R190/10^6 -> 4.9866817
D53: RAR | E53: Eurobank | F53: Used | G53: Cash loan | J53: €M | K53: 5 | L53: =L45*1000*L191/10^6 -> 5.3833333 | M53: =M45*1000*M191/10^6 -> 5.5986667 | N53: =N45*1000*N191/10^6 -> 5.814 | O53: =O45*1000*O191/10^6 -> 6.0293333 | P53: =P45*1000*P191/10^6 -> 6.2446667 | Q53: =Q45*1000*Q191/10^6 -> 6.5726818 | R53: =R45*1000*R191/10^6 -> 6.5726818
D54: RAR | E54: Eurobank | F54: Total | G54: Total | J54: €M | K54: =SUM(K51:K53) -> 19.3 | L54: =SUM(L51:L53) -> 19.941669 | M54: =SUM(M51:M53) -> 20.925894 | N54: =SUM(N51:N53) -> 21.910119 | O54: =SUM(O51:O53) -> 22.567121 | P54: =SUM(P51:P53) -> 23.224124 | Q54: =SUM(Q51:Q53) -> 23.993808 | R54: =SUM(R51:R53) -> 23.993808
D55: Opex | E55: Eurobank | F55: New | G55: Auto loan | J55: €M | K55: =K51*_xlfn.XLOOKUP($G55&$F55,$C$196:$C$198,K$196:K$198,,0) -> 2.9333286 | L55: =L51*_xlfn.XLOOKUP($G55&$F55,$C$196:$C$198,L$196:L$198,,0) -> 2.7388464 | M55: =M51*_xlfn.XLOOKUP($G55&$F55,$C$196:$C$198,M$196:M$198,,0) -> 2.6635864 | N55: =N51*_xlfn.XLOOKUP($G55&$F55,$C$196:$C$198,N$196:N$198,,0) -> 2.5577857 | O55: =O51*_xlfn.XLOOKUP($G55&$F55,$C$196:$C$198,O$196:O$198,,0) -> 2.356 | P55: =P51*_xlfn.XLOOKUP($G55&$F55,$C$196:$C$198,P$196:P$198,,0) -> 2.4214444 | Q55: =Q51*_xlfn.XLOOKUP($G55&$F55,$C$196:$C$198,Q$196:Q$198,,0) -> 2.4868889 | R55: =R51*_xlfn.XLOOKUP($G55&$F55,$C$196:$C$198,R$196:R$198,,0) -> 3.1086111 | S55: Considered 25-20% Opex/RAR, starting from 29% in 2024 (source ERB P&L) and gradually decreasing to 20% in 2030
D56: Opex | E56: Eurobank | F56: Used | G56: Auto loan | J56: €M | K56: =K52*_xlfn.XLOOKUP($G56&$F56,$C$196:$C$198,K$196:K$198,,0) -> 0.602 | L56: =L52*_xlfn.XLOOKUP($G56&$F56,$C$196:$C$198,L$196:L$198,,0) -> 0.582707 | M56: =M52*_xlfn.XLOOKUP($G56&$F56,$C$196:$C$198,M$196:M$198,,0) -> 0.56158284 | N56: =N52*_xlfn.XLOOKUP($G56&$F56,$C$196:$C$198,N$196:N$198,,0) -> 0.53862754 | O56: =O52*_xlfn.XLOOKUP($G56&$F56,$C$196:$C$198,O$196:O$198,,0) -> 0.51384108 | P56: =P52*_xlfn.XLOOKUP($G56&$F56,$C$196:$C$198,P$196:P$198,,0) -> 0.48722347 | Q56: =Q52*_xlfn.XLOOKUP($G56&$F56,$C$196:$C$198,Q$196:Q$198,,0) -> 0.5984018 | R56: =R52*_xlfn.XLOOKUP($G56&$F56,$C$196:$C$198,R$196:R$198,,0) -> 0.74800225 | S56: Considered 10-15% Opex/RAR, starting from 15% in 2024 (source ERB P&L) and gradually decreasing to 12% in 2030
D57: Opex | E57: Eurobank | F57: Used | G57: Cash loan | J57: €M | K57: =K53*_xlfn.XLOOKUP($G57&$F57,$C$196:$C$198,K$196:K$198,,0) -> 0.75 | L57: =L53*_xlfn.XLOOKUP($G57&$F57,$C$196:$C$198,L$196:L$198,,0) -> 0.8075 | M57: =M53*_xlfn.XLOOKUP($G57&$F57,$C$196:$C$198,M$196:M$198,,0) -> 0.8398 | N57: =N53*_xlfn.XLOOKUP($G57&$F57,$C$196:$C$198,N$196:N$198,,0) -> 0.8721 | O57: =O53*_xlfn.XLOOKUP($G57&$F57,$C$196:$C$198,O$196:O$198,,0) -> 0.9044 | P57: =P53*_xlfn.XLOOKUP($G57&$F57,$C$196:$C$198,P$196:P$198,,0) -> 0.9367 | Q57: =Q53*_xlfn.XLOOKUP($G57&$F57,$C$196:$C$198,Q$196:Q$198,,0) -> 0.98590227 | R57: =R53*_xlfn.XLOOKUP($G57&$F57,$C$196:$C$198,R$196:R$198,,0) -> 0.98590227 | S57: Considered 15% Opex/RAR - to be checked against cash loan incidence of Opex/ RAR
D58: Opex | E58: Eurobank | F58: Total | G58: Total | J58: €M | K58: =SUM(K55:K57) -> 4.2853286 | L58: =SUM(L55:L57) -> 4.1290534 | M58: =SUM(M55:M57) -> 4.0649692 | N58: =SUM(N55:N57) -> 3.9685132 | O58: =SUM(O55:O57) -> 3.7742411 | P58: =SUM(P55:P57) -> 3.8453679 | Q58: =SUM(Q55:Q57) -> 4.071193 | R58: =SUM(R55:R57) -> 4.8425156
D59: PBT | E59: Eurobank | F59: New | G59: Auto loan | J59: €M | K59: =K51-K55 -> 7.0666714 | L59: =L51-L55 -> 7.4050425 | M59: =M51-M55 -> 8.134747 | N59: =N51-N55 -> 8.8949921 | O59: =O51-O55 -> 9.424 | P59: =P51-P55 -> 9.6857778 | Q59: =Q51-Q55 -> 9.9475556 | R59: =R51-R55 -> 9.3258333
D60: PBT | E60: Eurobank | F60: Used | G60: Auto loan | J60: €M | K60: =K52-K56 -> 3.698 | L60: =L52-L56 -> 3.83174 | M60: =M52-M56 -> 3.9673111 | N60: =N52-N56 -> 4.1047133 | O60: =O52-O56 -> 4.2439467 | P60: =P52-P56 -> 4.3850113 | Q60: =Q52-Q56 -> 4.3882799 | R60: =R52-R56 -> 4.2386794
D61: PBT | E61: Eurobank | F61: Used | G61: Cash loan | J61: €M | K61: =K53-K57 -> 4.25 | L61: =L53-L57 -> 4.5758333 | M61: =M53-M57 -> 4.7588667 | N61: =N53-N57 -> 4.9419 | O61: =O53-O57 -> 5.1249333 | P61: =P53-P57 -> 5.3079667 | Q61: =Q53-Q57 -> 5.5867795 | R61: =R53-R57 -> 5.5867795
D62: PBT | E62: Eurobank | F62: Total | G62: Total | J62: €M | K62: =SUM(K59:K61) -> 15.014671 | L62: =SUM(L59:L61) -> 15.812616 | M62: =SUM(M59:M61) -> 16.860925 | N62: =SUM(N59:N61) -> 17.941605 | O62: =SUM(O59:O61) -> 18.79288 | P62: =SUM(P59:P61) -> 19.378756 | Q62: =SUM(Q59:Q61) -> 19.922615 | R62: =SUM(R59:R61) -> 19.151292
D63: Capex | E63: Eurobank | F63: Total | G63: Total
D65: Incremental business case
D66: KPI | K66: 2024 | L66: =K66+1 -> 2025 | M66: =L66+1 -> 2026 | N66: =M66+1 -> 2027 | O66: =N66+1 -> 2028 | P66: =O66+1 -> 2029 | Q66: =P66+1 -> 2030 | S66: Notes
Q67: Min | R67: Max
D68: Cars financed | E68: Eurobank | F68: New | G68: Auto loan | J68: k# | K68: =SUMIFS(K$104:K$174,$G$104:$G$174,$G68,$F$104:$F$174,$F68,$D$104:$D$174,$D68) -> 0 | L68: =SUMIFS(L$104:L$174,$G$104:$G$174,$G68,$F$104:$F$174,$F68,$D$104:$D$174,$D68) -> 0.055887097 | M68: =SUMIFS(M$104:M$174,$G$104:$G$174,$G68,$F$104:$F$174,$F68,$D$104:$D$174,$D68) -> 0.8904 | N68: =SUMIFS(N$104:N$174,$G$104:$G$174,$G68,$F$104:$F$174,$F68,$D$104:$D$174,$D68) -> 1.0238436 | O68: =SUMIFS(O$104:O$174,$G$104:$G$174,$G68,$F$104:$F$174,$F68,$D$104:$D$174,$D68) -> 1.1627641 | P68: =SUMIFS(P$104:P$174,$G$104:$G$174,$G68,$F$104:$F$174,$F68,$D$104:$D$174,$D68) -> 1.3067616 | Q68: =SUMIFS(Q$104:Q$174,$G$104:$G$174,$G68,$F$104:$F$174,$F68,$D$104:$D$174,$D68) -> 1.767273 | R68: =SUMIFS(R$104:R$174,$G$104:$G$174,$G68,$F$104:$F$174,$F68,$D$104:$D$174,$D68) -> 2.4848233 | W68: 175
D69: Cars financed | E69: Eurobank | F69: Used | G69: Auto loan | J69: k# | K69: =SUMIFS(K$104:K$174,$G$104:$G$174,$G69,$F$104:$F$174,$F69,$D$104:$D$174,$D69) -> 0 | L69: =SUMIFS(L$104:L$174,$G$104:$G$174,$G69,$F$104:$F$174,$F69,$D$104:$D$174,$D69) -> 0.043619548 | M69: =SUMIFS(M$104:M$174,$G$104:$G$174,$G69,$F$104:$F$174,$F69,$D$104:$D$174,$D69) -> 3.1953088 | N69: =SUMIFS(N$104:N$174,$G$104:$G$174,$G69,$F$104:$F$174,$F69,$D$104:$D$174,$D69) -> 3.559824 | O69: =SUMIFS(O$104:O$174,$G$104:$G$174,$G69,$F$104:$F$174,$F69,$D$104:$D$174,$D69) -> 6.0025111 | P69: =SUMIFS(P$104:P$174,$G$104:$G$174,$G69,$F$104:$F$174,$F69,$D$104:$D$174,$D69) -> 6.5273975 | Q69: =SUMIFS(Q$104:Q$174,$G$104:$G$174,$G69,$F$104:$F$174,$F69,$D$104:$D$174,$D69) -> 7.7174832 | R69: =SUMIFS(R$104:R$174,$G$104:$G$174,$G69,$F$104:$F$174,$F69,$D$104:$D$174,$D69) -> 8.6290402 | W69: 27
D70: Cars financed | E70: Eurobank | F70: Used | G70: Cash loan | J70: k# | K70: =SUMIFS(K$104:K$174,$G$104:$G$174,$G70,$F$104:$F$174,$F70,$D$104:$D$174,$D70) -> 0 | L70: =SUMIFS(L$104:L$174,$G$104:$G$174,$G70,$F$104:$F$174,$F70,$D$104:$D$174,$D70) -> 0 | M70: =SUMIFS(M$104:M$174,$G$104:$G$174,$G70,$F$104:$F$174,$F70,$D$104:$D$174,$D70) -> 0.21333333 | N70: =SUMIFS(N$104:N$174,$G$104:$G$174,$G70,$F$104:$F$174,$F70,$D$104:$D$174,$D70) -> 0.72882204 | O70: =SUMIFS(O$104:O$174,$G$104:$G$174,$G70,$F$104:$F$174,$F70,$D$104:$D$174,$D70) -> 1.2522761 | P70: =SUMIFS(P$104:P$174,$G$104:$G$174,$G70,$F$104:$F$174,$F70,$D$104:$D$174,$D70) -> 1.7836039 | Q70: =SUMIFS(Q$104:Q$174,$G$104:$G$174,$G70,$F$104:$F$174,$F70,$D$104:$D$174,$D70) -> 1.9576496 | R70: =SUMIFS(R$104:R$174,$G$104:$G$174,$G70,$F$104:$F$174,$F70,$D$104:$D$174,$D70) -> 3.3152992 | W70: 34
D71: Cars financed | E71: Eurobank | F71: Total | G71: Total | J71: k# | K71: =SUM(K68:K70) -> 0 | L71: =SUM(L68:L70) -> 0.099506645 | M71: =SUM(M68:M70) -> 4.2990421 | N71: =SUM(N68:N70) -> 5.3124896 | O71: =SUM(O68:O70) -> 8.4175513 | P71: =SUM(P68:P70) -> 9.617763 | Q71: =SUM(Q68:Q70) -> 11.442406 | R71: =SUM(R68:R70) -> 14.429163 | W71: 63
D72: Loan disbursements | E72: Eurobank | F72: New | G72: Auto loan | J72: €M | K72: =SUMIFS(K$104:K$174,$G$104:$G$174,$G72,$F$104:$F$174,$F72,$D$104:$D$174,$D72) -> 0 | L72: =SUMIFS(L$104:L$174,$G$104:$G$174,$G72,$F$104:$F$174,$F72,$D$104:$D$174,$D72) -> 0.83830645 | M72: =SUMIFS(M$104:M$174,$G$104:$G$174,$G72,$F$104:$F$174,$F72,$D$104:$D$174,$D72) -> 14.018455 | N72: =SUMIFS(N$104:N$174,$G$104:$G$174,$G72,$F$104:$F$174,$F72,$D$104:$D$174,$D72) -> 16.505641 | O72: =SUMIFS(O$104:O$174,$G$104:$G$174,$G72,$F$104:$F$174,$F72,$D$104:$D$174,$D72) -> 19.186961 | P72: =SUMIFS(P$104:P$174,$G$104:$G$174,$G72,$F$104:$F$174,$F72,$D$104:$D$174,$D72) -> 22.062415 | Q72: =SUMIFS(Q$104:Q$174,$G$104:$G$174,$G72,$F$104:$F$174,$F72,$D$104:$D$174,$D72) -> 30.555872 | R72: =SUMIFS(R$104:R$174,$G$104:$G$174,$G72,$F$104:$F$174,$F72,$D$104:$D$174,$D72) -> 43.224498 | S72: =34+63+46 -> 143 | W72: 46
D73: Loan disbursements | E73: Eurobank | F73: Used | G73: Auto loan | J73: €M | K73: =SUMIFS(K$104:K$174,$G$104:$G$174,$G73,$F$104:$F$174,$F73,$D$104:$D$174,$D73) -> 0 | L73: =SUMIFS(L$104:L$174,$G$104:$G$174,$G73,$F$104:$F$174,$F73,$D$104:$D$174,$D73) -> 1.1795993 | M73: =SUMIFS(M$104:M$174,$G$104:$G$174,$G73,$F$104:$F$174,$F73,$D$104:$D$174,$D73) -> 33.478899 | N73: =SUMIFS(N$104:N$174,$G$104:$G$174,$G73,$F$104:$F$174,$F73,$D$104:$D$174,$D73) -> 38.778949 | O73: =SUMIFS(O$104:O$174,$G$104:$G$174,$G73,$F$104:$F$174,$F73,$D$104:$D$174,$D73) -> 66.107163 | P73: =SUMIFS(P$104:P$174,$G$104:$G$174,$G73,$F$104:$F$174,$F73,$D$104:$D$174,$D73) -> 74.026366 | Q73: =SUMIFS(Q$104:Q$174,$G$104:$G$174,$G73,$F$104:$F$174,$F73,$D$104:$D$174,$D73) -> 89.539002 | R73: =SUMIFS(R$104:R$174,$G$104:$G$174,$G73,$F$104:$F$174,$F73,$D$104:$D$174,$D73) -> 99.618153 | S73: =+S72+175 -> 318 | W73: =SUM(W68:W72) -> 345
D74: Loan disbursements | E74: Eurobank | F74: Used | G74: Cash loan | J74: €M | K74: =SUMIFS(K$104:K$174,$G$104:$G$174,$G74,$F$104:$F$174,$F74,$D$104:$D$174,$D74) -> 0 | L74: =SUMIFS(L$104:L$174,$G$104:$G$174,$G74,$F$104:$F$174,$F74,$D$104:$D$174,$D74) -> 0 | M74: =SUMIFS(M$104:M$174,$G$104:$G$174,$G74,$F$104:$F$174,$F74,$D$104:$D$174,$D74) -> 1.1234465 | N74: =SUMIFS(N$104:N$174,$G$104:$G$174,$G74,$F$104:$F$174,$F74,$D$104:$D$174,$D74) -> 3.9350804 | O74: =SUMIFS(O$104:O$174,$G$104:$G$174,$G74,$F$104:$F$174,$F74,$D$104:$D$174,$D74) -> 6.9279812 | P74: =SUMIFS(P$104:P$174,$G$104:$G$174,$G74,$F$104:$F$174,$F74,$D$104:$D$174,$D74) -> 10.10481 | Q74: =SUMIFS(Q$104:Q$174,$G$104:$G$174,$G74,$F$104:$F$174,$F74,$D$104:$D$174,$D74) -> 11.351367 | R74: =SUMIFS(R$104:R$174,$G$104:$G$174,$G74,$F$104:$F$174,$F74,$D$104:$D$174,$D74) -> 19.223654 | S74: =+S73-345 -> -27
D75: Cars financed | E75: Eurobank | F75: Total | G75: Total | J75: k# | K75: =SUM(K72:K74) -> 0 | L75: =SUM(L72:L74) -> 2.0179057 | M75: =SUM(M72:M74) -> 48.620801 | N75: =SUM(N72:N74) -> 59.219671 | O75: =SUM(O72:O74) -> 92.222105 | P75: =SUM(P72:P74) -> 106.19359 | Q75: =SUM(Q72:Q74) -> 131.44624 | R75: =SUM(R72:R74) -> 162.0663
D76: RAR | E76: Eurobank | F76: New | G76: Auto loan | J76: €M | K76: =SUMIFS(K$104:K$174,$G$104:$G$174,$G76,$F$104:$F$174,$F76,$D$104:$D$174,$D76) -> 0 | L76: =SUMIFS(L$104:L$174,$G$104:$G$174,$G76,$F$104:$F$174,$F76,$D$104:$D$174,$D76) -> 0.0548625 | M76: =SUMIFS(M$104:M$174,$G$104:$G$174,$G76,$F$104:$F$174,$F76,$D$104:$D$174,$D76) -> 0.91743 | N76: =SUMIFS(N$104:N$174,$G$104:$G$174,$G76,$F$104:$F$174,$F76,$D$104:$D$174,$D76) -> 1.0802025 | O76: =SUMIFS(O$104:O$174,$G$104:$G$174,$G76,$F$104:$F$174,$F76,$D$104:$D$174,$D76) -> 1.25568 | P76: =SUMIFS(P$104:P$174,$G$104:$G$174,$G76,$F$104:$F$174,$F76,$D$104:$D$174,$D76) -> 1.4438625 | Q76: =SUMIFS(Q$104:Q$174,$G$104:$G$174,$G76,$F$104:$F$174,$F76,$D$104:$D$174,$D76) -> 1.9997121 | R76: =SUMIFS(R$104:R$174,$G$104:$G$174,$G76,$F$104:$F$174,$F76,$D$104:$D$174,$D76) -> 2.8288033
D77: RAR | E77: Eurobank | F77: Used | G77: Auto loan | J77: €M | K77: =SUMIFS(K$104:K$174,$G$104:$G$174,$G77,$F$104:$F$174,$F77,$D$104:$D$174,$D77) -> 0 | L77: =SUMIFS(L$104:L$174,$G$104:$G$174,$G77,$F$104:$F$174,$F77,$D$104:$D$174,$D77) -> 0.16933803 | M77: =SUMIFS(M$104:M$174,$G$104:$G$174,$G77,$F$104:$F$174,$F77,$D$104:$D$174,$D77) -> 4.1328294 | N77: =SUMIFS(N$104:N$174,$G$104:$G$174,$G77,$F$104:$F$174,$F77,$D$104:$D$174,$D77) -> 4.7683897 | O77: =SUMIFS(O$104:O$174,$G$104:$G$174,$G77,$F$104:$F$174,$F77,$D$104:$D$174,$D77) -> 8.5363923 | P77: =SUMIFS(P$104:P$174,$G$104:$G$174,$G77,$F$104:$F$174,$F77,$D$104:$D$174,$D77) -> 9.4852197 | Q77: =SUMIFS(Q$104:Q$174,$G$104:$G$174,$G77,$F$104:$F$174,$F77,$D$104:$D$174,$D77) -> 11.30288 | R77: =SUMIFS(R$104:R$174,$G$104:$G$174,$G77,$F$104:$F$174,$F77,$D$104:$D$174,$D77) -> 12.602903
D78: RAR | E78: Eurobank | F78: Used | G78: Cash loan | J78: €M | K78: =SUMIFS(K$104:K$174,$G$104:$G$174,$G78,$F$104:$F$174,$F78,$D$104:$D$174,$D78) -> 0 | L78: =SUMIFS(L$104:L$174,$G$104:$G$174,$G78,$F$104:$F$174,$F78,$D$104:$D$174,$D78) -> 0 | M78: =SUMIFS(M$104:M$174,$G$104:$G$174,$G78,$F$104:$F$174,$F78,$D$104:$D$174,$D78) -> 0.1275736 | N78: =SUMIFS(N$104:N$174,$G$104:$G$174,$G78,$F$104:$F$174,$F78,$D$104:$D$174,$D78) -> 0.51145024 | O78: =SUMIFS(O$104:O$174,$G$104:$G$174,$G78,$F$104:$F$174,$F78,$D$104:$D$174,$D78) -> 0.91931075 | P78: =SUMIFS(P$104:P$174,$G$104:$G$174,$G78,$F$104:$F$174,$F78,$D$104:$D$174,$D78) -> 1.3514574 | Q78: =SUMIFS(Q$104:Q$174,$G$104:$G$174,$G78,$F$104:$F$174,$F78,$D$104:$D$174,$D78) -> 1.5043049 | R78: =SUMIFS(R$104:R$174,$G$104:$G$174,$G78,$F$104:$F$174,$F78,$D$104:$D$174,$D78) -> 2.6135409
D79: RAR | E79: Eurobank | F79: Total | G79: Total | J79: €M | K79: =SUM(K76:K78) -> 0 | L79: =SUM(L76:L78) -> 0.22420053 | M79: =SUM(M76:M78) -> 5.177833 | N79: =SUM(N76:N78) -> 6.3600424 | O79: =SUM(O76:O78) -> 10.711383 | P79: =SUM(P76:P78) -> 12.28054 | Q79: =SUM(Q76:Q78) -> 14.806897 | R79: =SUM(R76:R78) -> 18.045247
B80: Highly preliminary | D80: Opex | E80: Eurobank | F80: New | G80: Auto loan | J80: €M | K80: =SUMIFS(K$104:K$174,$G$104:$G$174,$G80,$F$104:$F$174,$F80,$D$104:$D$174,$D80) -> 0 | L80: =SUMIFS(L$104:L$174,$G$104:$G$174,$G80,$F$104:$F$174,$F80,$D$104:$D$174,$D80) -> 0.014812856 | M80: =SUMIFS(M$104:M$174,$G$104:$G$174,$G80,$F$104:$F$174,$F80,$D$104:$D$174,$D80) -> 0.22629918 | N80: =SUMIFS(N$104:N$174,$G$104:$G$174,$G80,$F$104:$F$174,$F80,$D$104:$D$174,$D80) -> 0.2412451 | O80: =SUMIFS(O$104:O$174,$G$104:$G$174,$G80,$F$104:$F$174,$F80,$D$104:$D$174,$D80) -> 0.251136 | P80: =SUMIFS(P$104:P$174,$G$104:$G$174,$G80,$F$104:$F$174,$F80,$D$104:$D$174,$D80) -> 0.2887725 | Q80: =SUMIFS(Q$104:Q$174,$G$104:$G$174,$G80,$F$104:$F$174,$F80,$D$104:$D$174,$D80) -> 0.39994242 | R80: =SUMIFS(R$104:R$174,$G$104:$G$174,$G80,$F$104:$F$174,$F80,$D$104:$D$174,$D80) -> 0.70720082 | S80: Considered 25-20% Opex/RAR, starting from 29% in 2024 (source ERB P&L) and gradually decreasing to 20% in 2030
B81: Highly preliminary | D81: Opex | E81: Eurobank | F81: Used | G81: Auto loan | J81: €M | K81: =SUMIFS(K$104:K$174,$G$104:$G$174,$G81,$F$104:$F$174,$F81,$D$104:$D$174,$D81) -> 0 | L81: =SUMIFS(L$104:L$174,$G$104:$G$174,$G81,$F$104:$F$174,$F81,$D$104:$D$174,$D81) -> 0.02235262 | M81: =SUMIFS(M$104:M$174,$G$104:$G$174,$G81,$F$104:$F$174,$F81,$D$104:$D$174,$D81) -> 0.51247085 | N81: =SUMIFS(N$104:N$174,$G$104:$G$174,$G81,$F$104:$F$174,$F81,$D$104:$D$174,$D81) -> 0.5531332 | O81: =SUMIFS(O$104:O$174,$G$104:$G$174,$G81,$F$104:$F$174,$F81,$D$104:$D$174,$D81) -> 0.92193037 | P81: =SUMIFS(P$104:P$174,$G$104:$G$174,$G81,$F$104:$F$174,$F81,$D$104:$D$174,$D81) -> 0.94852197 | Q81: =SUMIFS(Q$104:Q$174,$G$104:$G$174,$G81,$F$104:$F$174,$F81,$D$104:$D$174,$D81) -> 1.3563456 | R81: =SUMIFS(R$104:R$174,$G$104:$G$174,$G81,$F$104:$F$174,$F81,$D$104:$D$174,$D81) -> 1.8904355 | S81: Considered 10-15% Opex/RAR, starting from 15% in 2024 (source ERB P&L) and gradually decreasing to 10% in 2030
B82: Highly preliminary | D82: Opex | E82: Eurobank | F82: Used | G82: Cash loan | J82: €M | K82: =SUMIFS(K$104:K$174,$G$104:$G$174,$G82,$F$104:$F$174,$F82,$D$104:$D$174,$D82) -> 0 | L82: =SUMIFS(L$104:L$174,$G$104:$G$174,$G82,$F$104:$F$174,$F82,$D$104:$D$174,$D82) -> 0 | M82: =SUMIFS(M$104:M$174,$G$104:$G$174,$G82,$F$104:$F$174,$F82,$D$104:$D$174,$D82) -> 0.01913604 | N82: =SUMIFS(N$104:N$174,$G$104:$G$174,$G82,$F$104:$F$174,$F82,$D$104:$D$174,$D82) -> 0.076717536 | O82: =SUMIFS(O$104:O$174,$G$104:$G$174,$G82,$F$104:$F$174,$F82,$D$104:$D$174,$D82) -> 0.13789661 | P82: =SUMIFS(P$104:P$174,$G$104:$G$174,$G82,$F$104:$F$174,$F82,$D$104:$D$174,$D82) -> 0.2027186 | Q82: =SUMIFS(Q$104:Q$174,$G$104:$G$174,$G82,$F$104:$F$174,$F82,$D$104:$D$174,$D82) -> 0.22564573 | R82: =SUMIFS(R$104:R$174,$G$104:$G$174,$G82,$F$104:$F$174,$F82,$D$104:$D$174,$D82) -> 0.39203113 | S82: Considered 15% Opex/RAR - to be checked against cash loan incidence of Opex/ RAR
B83: Highly preliminary | D83: Opex | E83: Eurobank | F83: Total | G83: Total | J83: €M | K83: =SUM(K80:K82) -> 0 | L83: =SUM(L80:L82) -> 0.037165476 | M83: =SUM(M80:M82) -> 0.75790607 | N83: =SUM(N80:N82) -> 0.87109584 | O83: =SUM(O80:O82) -> 1.310963 | P83: =SUM(P80:P82) -> 1.4400131 | Q83: =SUM(Q80:Q82) -> 1.9819337 | R83: =SUM(R80:R82) -> 2.9896674
D84: PBT | E84: Eurobank | F84: New | G84: Auto loan | J84: €M | K84: =SUMIFS(K$104:K$174,$G$104:$G$174,$G84,$F$104:$F$174,$F84,$D$104:$D$174,$D84) -> 0 | L84: =SUMIFS(L$104:L$174,$G$104:$G$174,$G84,$F$104:$F$174,$F84,$D$104:$D$174,$D84) -> 0.040049644 | M84: =SUMIFS(M$104:M$174,$G$104:$G$174,$G84,$F$104:$F$174,$F84,$D$104:$D$174,$D84) -> 0.69113082 | N84: =SUMIFS(N$104:N$174,$G$104:$G$174,$G84,$F$104:$F$174,$F84,$D$104:$D$174,$D84) -> 0.8389574 | O84: =SUMIFS(O$104:O$174,$G$104:$G$174,$G84,$F$104:$F$174,$F84,$D$104:$D$174,$D84) -> 1.004544 | P84: =SUMIFS(P$104:P$174,$G$104:$G$174,$G84,$F$104:$F$174,$F84,$D$104:$D$174,$D84) -> 1.15509 | Q84: =SUMIFS(Q$104:Q$174,$G$104:$G$174,$G84,$F$104:$F$174,$F84,$D$104:$D$174,$D84) -> 1.5997697 | R84: =SUMIFS(R$104:R$174,$G$104:$G$174,$G84,$F$104:$F$174,$F84,$D$104:$D$174,$D84) -> 2.1216025
D85: PBT | E85: Eurobank | F85: Used | G85: Auto loan | J85: €M | K85: =SUMIFS(K$104:K$174,$G$104:$G$174,$G85,$F$104:$F$174,$F85,$D$104:$D$174,$D85) -> 0 | L85: =SUMIFS(L$104:L$174,$G$104:$G$174,$G85,$F$104:$F$174,$F85,$D$104:$D$174,$D85) -> 0.14698541 | M85: =SUMIFS(M$104:M$174,$G$104:$G$174,$G85,$F$104:$F$174,$F85,$D$104:$D$174,$D85) -> 3.6203586 | N85: =SUMIFS(N$104:N$174,$G$104:$G$174,$G85,$F$104:$F$174,$F85,$D$104:$D$174,$D85) -> 4.2152565 | O85: =SUMIFS(O$104:O$174,$G$104:$G$174,$G85,$F$104:$F$174,$F85,$D$104:$D$174,$D85) -> 7.6144619 | P85: =SUMIFS(P$104:P$174,$G$104:$G$174,$G85,$F$104:$F$174,$F85,$D$104:$D$174,$D85) -> 8.5366977 | Q85: =SUMIFS(Q$104:Q$174,$G$104:$G$174,$G85,$F$104:$F$174,$F85,$D$104:$D$174,$D85) -> 9.9465341 | R85: =SUMIFS(R$104:R$174,$G$104:$G$174,$G85,$F$104:$F$174,$F85,$D$104:$D$174,$D85) -> 10.712468
D86: PBT | E86: Eurobank | F86: Used | G86: Cash loan | J86: €M | K86: =SUMIFS(K$104:K$174,$G$104:$G$174,$G86,$F$104:$F$174,$F86,$D$104:$D$174,$D86) -> 0 | L86: =SUMIFS(L$104:L$174,$G$104:$G$174,$G86,$F$104:$F$174,$F86,$D$104:$D$174,$D86) -> 0 | M86: =SUMIFS(M$104:M$174,$G$104:$G$174,$G86,$F$104:$F$174,$F86,$D$104:$D$174,$D86) -> 0.10843756 | N86: =SUMIFS(N$104:N$174,$G$104:$G$174,$G86,$F$104:$F$174,$F86,$D$104:$D$174,$D86) -> 0.43473271 | O86: =SUMIFS(O$104:O$174,$G$104:$G$174,$G86,$F$104:$F$174,$F86,$D$104:$D$174,$D86) -> 0.78141414 | P86: =SUMIFS(P$104:P$174,$G$104:$G$174,$G86,$F$104:$F$174,$F86,$D$104:$D$174,$D86) -> 1.1487388 | Q86: =SUMIFS(Q$104:Q$174,$G$104:$G$174,$G86,$F$104:$F$174,$F86,$D$104:$D$174,$D86) -> 1.2786592 | R86: =SUMIFS(R$104:R$174,$G$104:$G$174,$G86,$F$104:$F$174,$F86,$D$104:$D$174,$D86) -> 2.2215098
D87: PBT | E87: Eurobank | F87: Total | G87: Total | J87: €M | K87: =SUM(K84:K86) -> 0 | L87: =SUM(L84:L86) -> 0.18703505 | M87: =SUM(M84:M86) -> 4.4199269 | N87: =SUM(N84:N86) -> 5.4889466 | O87: =SUM(O84:O86) -> 9.40042 | P87: =SUM(P84:P86) -> 10.840527 | Q87: =SUM(Q84:Q86) -> 12.824963 | R87: =SUM(R84:R86) -> 15.05558
D88: Capex | E88: Eurobank | F88: Total | G88: Total | K88: =SUMIFS(K$104:K$174,$G$104:$G$174,$G88,$F$104:$F$174,$F88,$D$104:$D$174,$D88) -> 0 | L88: =SUMIFS(L$104:L$174,$G$104:$G$174,$G88,$F$104:$F$174,$F88,$D$104:$D$174,$D88) -> 0.4 | M88: =SUMIFS(M$104:M$174,$G$104:$G$174,$G88,$F$104:$F$174,$F88,$D$104:$D$174,$D88) -> 1.5 | N88: =SUMIFS(N$104:N$174,$G$104:$G$174,$G88,$F$104:$F$174,$F88,$D$104:$D$174,$D88) -> 0 | O88: =SUMIFS(O$104:O$174,$G$104:$G$174,$G88,$F$104:$F$174,$F88,$D$104:$D$174,$D88) -> 0 | P88: =SUMIFS(P$104:P$174,$G$104:$G$174,$G88,$F$104:$F$174,$F88,$D$104:$D$174,$D88) -> 0 | Q88: =SUMIFS(Q$104:Q$174,$G$104:$G$174,$G88,$F$104:$F$174,$F88,$D$104:$D$174,$D88) -> 0 | R88: =SUMIFS(R$104:R$174,$G$104:$G$174,$G88,$F$104:$F$174,$F88,$D$104:$D$174,$D88) -> 0
L89: =+G104&F104 -> Auto loanNew | M89: =+M104*1000 -> 121.48313 | N89: =+N104*1000 -> 196.05204 | O89: =+O104*1000 -> 278.93037
L90: =+G105&F105 -> Auto loanUsed | M90: =+M105*1000 -> 175.78914 | N90: =+N105*1000 -> 376.93615 | O90: =+O105*1000 -> 658.2938
L91: =+G106&F106 -> Cash loanUsed | M91: =+M106*1000 -> 213.33333 | N91: =+N106*1000 -> 728.82204 | O91: =+O106*1000 -> 1252.2761
L92: =+L89 -> Auto loanNew | M92: =+M108*1000000 -> 1870747 | N92: =+N108*1000000 -> 3097321.7 | O92: =+O108*1000000 -> 4518030.6
L93: =+L90 -> Auto loanUsed | M93: =+M109*1000000 -> 1749416.8 | N93: =+N109*1000000 -> 3851523.6 | O93: =+O109*1000000 -> 6897827
L94: =+L91 -> Cash loanUsed | M94: =+M110*1000000 -> 1123446.5 | N94: =+N110*1000000 -> 3935080.4 | O94: =+O110*1000000 -> 6927981.2
L95: =+L92 -> Auto loanNew | M95: =+M92/M89 -> 15399.234 | N95: =+N92/N89 -> 15798.467 | O95: =+O92/O89 -> 16197.701
L96: =+L93 -> Auto loanUsed | M96: =+M93/M90 -> 9951.7911 | N96: =+N93/N90 -> 10217.974 | O96: =+O93/O90 -> 10478.341
L97: =+L94 -> Cash loanUsed | M97: =+M94/M91 -> 5266.1557 | N97: =+N94/N91 -> 5399.2335 | O97: =+O94/O91 -> 5532.3114
D101: Expand digital presence
J102: UoM | K102: 2024 | L102: 2025 | M102: 2026 | N102: 2027 | O102: 2028 | P102: 2029 | Q102: 2030
D103: KPI | F103: Car type | G103: Product | Q103: Min | R103: Max
D104: Cars financed | E104: Eurobank | F104: New | G104: Auto loan | J104: k# | K104: 0 | L104: 0.055887097 | M104: 0.12148313 | N104: 0.19605204 | O104: 0.27893037 | P104: 0.36951846 | Q104: 0.46727302 | R104: 0.68482329
D105: Cars financed | E105: Eurobank | F105: Used | G105: Auto loan | J105: k# | K105: 0 | L105: 0.017240712 | M105: 0.17578914 | N105: 0.37693615 | O105: 0.6582938 | P105: 1.023746 | Q105: 1.4774832 | R105: 1.9890402 | S105: =+M105*1000 -> 175.78914 | T105: =+N105*1000 -> 376.93615 | U105: =+O105*1000 -> 658.2938
...

Sheet McKinsey
M1: 2024 | N1: 2025 | O1: 2026 | P1: 2027 | Q1: 2028 | T1: 2024
T2: sales | U2: loans | V2: finance penetration
I3: Market | J3: New | K3: no. of loans | L3: k# | M3: 24.666667 | N3: 27.274085 | O3: 29.749722 | P3: 32.103322 | Q3: 34.343692 | S3: new | T3: 62 | U3: 25 | V3: =+U3/T3 -> 0.40322581
G4: =135*42% -> 56.7 | I4: Market | J4: Used | K4: =+K3 -> no. of loans | L4: k# | M4: 21.052632 | N4: 23.411965 | O4: 25.652056 | P4: 27.781721 | Q4: 29.80893 | S4: used | T4: 135 | U4: 21 | V4: =+U4/T4 -> 0.15555556
S5: total | T5: =+T4+T3 -> 197 | U5: =+U4+U3 -> 46 | V5: =+U5/T5 -> 0.23350254
I6: Market | J6: New | K6: disb. Amount | L6: €M | M6: =+M3*15 -> 370 | N6: 420 | O6: 470 | P6: 520 | Q6: 570
I7: Market | J7: Used | K7: =+K6 -> disb. Amount | L7: €M | M7: =+M4*9.5 -> 200 | N7: 228.33333 | O7: 256.66667 | P7: 285 | Q7: 313.33333
M8: 2024 | N8: 2025 | O8: 2026 | P8: 2027 | Q8: 2028
I9: Market | J9: New | K9: cars sales | L9: k# | M9: =+M3/V3 -> 61.173333 | N9: 66 | O9: 71 | P9: 74 | Q9: 77
I10: Market | J10: Used | K10: =+K9 -> cars sales | L10: k# | M10: =+M4/V4 -> 135.33835 | N10: =+M10 -> 135.33835 | O10: 144 | P10: 147 | Q10: 150
I12: Market | J12: New | K12: cars sales | L12: €M | M12: =+M9*15 -> 917.6 | N12: =+N9*(15*102%) -> 1009.8 | O12: =+O9*(15*102%) -> 1086.3 | P12: =+P9*(15*102%) -> 1132.2 | Q12: =+Q9*(15*102%) -> 1178.1
I13: Market | J13: Used | K13: =+K12 -> cars sales | L13: €M | M13: =+M10*8.5 -> 1150.3759 | N13: =+N10*(8.5*102%) -> 1173.3835 | O13: =+O10*(8.5*102%) -> 1248.48 | P13: =+P10*(8.5*102%) -> 1274.49 | Q13: =+Q10*(8.5*102%) -> 1300.5
I15: =+I12 -> Market | J15: =+J9 -> New | K15: annual growth | N15: =+N12/M12-1 -> 0.10047951 | O15: =+O12/N12-1 -> 0.075757576 | P15: =+P12/O12-1 -> 0.042253521 | Q15: =+Q12/P12-1 -> 0.040540541
I16: =+I15 -> Market | J16: =+J13 -> Used | K16: annual growth | N16: =+N13/M13-1 -> 0.02 | O16: =+O13/N13-1 -> 0.064 | P16: =+P13/O13-1 -> 0.020833333 | Q16: =+Q13/P13-1 -> 0.020408163
I17: =+I16 -> Market | J17: total | K17: annual growth | N17: =+(N12+N13)/(M12+M13)-1 -> 0.05571028 | O17: =+(O12+O13)/(N12+N13)-1 -> 0.069438297 | P17: =+(P12+P13)/(O12+O13)-1 -> 0.030799476 | Q17: =+(Q12+Q13)/(P12+P13)-1 -> 0.029879212
I18: =+I16 -> Market | J18: =+J15 -> New | K18: finance penetration | M18: =+M6/M12 -> 0.40322581 | N18: =+N6/N12 -> 0.41592395 | O18: =+O6/O12 -> 0.43266133 | P18: =+P6/P12 -> 0.45928281 | Q18: =+Q6/Q12 -> 0.4838299
I19: =+I18 -> Market | J19: =+J16 -> Used | K19: finance penetration | M19: =+M7/M13 -> 0.17385621 | N19: =+N7/N13 -> 0.19459396 | O19: =+O7/O13 -> 0.20558332 | P19: =+P7/P13 -> 0.22361886 | Q19: =+Q7/Q13 -> 0.24093297
B24: Sales (€M)=Loan penetrationAuto loans (€M)​ | N24: =+N12/M12-1 -> 0.10047951 | O24: =+O12/N12-1 -> 0.075757576 | P24: =+P12/O12-1 -> 0.042253521 | Q24: =+Q12/P12-1 -> 0.040540541
B25: +2% p.a.increse on car prices | N25: =+N13/M13-1 -> 0.02 | O25: =+O13/N13-1 -> 0.064 | P25: =+P13/O13-1 -> 0.020833333 | Q25: =+Q13/P13-1 -> 0.020408163
B26: new: 40% (2024) → 41% (2025) → 42% (2026) → 43% (2027) → 44% (2028)
B27: used: 16% (2024) → 17% (2025) → 18% (2026) → 19% (2027) → 20% (2028)
N28: =+N10+N9 -> 201.33835
B29: Έτος | C29: New Sales k# | D29: Used Sales k# | N29: =+N10/N28 -> 0.67219359
B30: 2024 | C30: 61 | D30: 135
B31: 2025 | C31: 27/41% = 66 | D31: 23/17% = 135
B32: 2026 | C32: 30/42% = 71 | D32: 26/18% = 144
B33: 2027 | C33: 32/43% = 74 | D33: 28/19% = 147
B34: 2028 | C34: 34/44% = 77 | D34: 30/20% = 150

Sheet sales analysis (MRKT)
A1: Έτος | B1: Εισαγόμενα (συνολικά) | C1: ετήσια αύξηση | D1: Επιβατικά ποσοστό | E1: Επιβατικά Εισαγόμενα | F1: Επιβ. Νέα ποσοστό | G1: Επιβ. Νέα Εισαγόμενα | H1: Επιβ. Μτχ Εισαγόμενα | I1: Μεταβιβ. Επιβ. Μτχ | J1: Νέα Retail ποσοστό | K1: Νέα Retail | L1: Νέα Wholesale ποσοστό | M1: Νέα Wholesale | N1: Μτχ Retail ποσοστό | O1: Μτχ Retail | P1: Μτχ Wholesale ποσοστό | Q1: Μτχ Wholesale
A2: 2024 | B2: 243796 | D2: =+E2/B2 -> 0.56235951 | E2: 137101 | F2: =+G2/E2 -> 0.70479428 | G2: 96628 | H2: 40473 | I2: 66527 | J2: =+K2/G2 -> 0.631287 | K2: 61000 | L2: =+M2/G2 -> 0.368713 | M2: 35628 | N2: =+O2/(H2+I2) -> 0.9 | O2: 96300 | P2: =+Q2/(H2+I2) -> 0.1 | Q2: 10700
A3: 2025 | B3: =+B2*C3+100%+B2 -> 248672.92 | C3: 0.02 | D3: 0.56235951 | E3: =+D3*B3 -> 139843.58 | F3: 0.70479428 | G3: =+F3*E3 -> 98560.956 | H3: =+E3-G3 -> 41282.626 | I3: 69000 | J3: =+K3/G3 -> 0.63919834 | K3: 63000 | L3: =+M3/G3 -> 0.3764168 | M3: 37100 | N3: =+O3/(H3+I3) -> 0.89315973 | O3: 98500 | P3: =+Q3/(H3+I3) -> 0.09520992 | Q3: 10500
A4: 2026 | B4: =+B3*C4+100%+B3 -> 253896.05 | C4: 0.021 | D4: 0.56235951 | E4: =+D4*B4 -> 142780.86 | F4: 0.70479428 | G4: =+F4*E4 -> 100631.13 | H4: =+E4-G4 -> 42149.727 | I4: 71500 | J4: =+K4/G4 -> 0.65089201 | K4: 65500 | L4: =+M4/G4 -> 0.38854775 | M4: 39100 | N4: =+O4/(H4+I4) -> 0.8860558 | O4: 100700 | P4: =+Q4/(H4+I4) -> 0.088869549 | Q4: 10100
A5: 2027 | B5: =+B4*C5+100%+B4 -> 259482.76 | C5: 0.022 | D5: 0.56235951 | E5: =+D5*B5 -> 145922.6 | F5: 0.70479428 | G5: =+F5*E5 -> 102845.41 | H5: =+E5-G5 -> 43077.187 | I5: 74000 | J5: =+K5/G5 -> 0.66118651 | K5: 68000 | L5: =+M5/G5 -> 0.4025459 | M5: 41400 | N5: =+O5/(H5+I5) -> 0.87890735 | O5: 102900 | P5: =+Q5/(H5+I5) -> 0.084559599 | Q5: 9900
A6: 2027 | B6: =+B5*C6+100%+B5 -> 265451.87 | C6: 0.023 | D6: 0.56235951 | E6: =+D6*B6 -> 149279.38 | F6: 0.70479428 | G6: =+F6*E6 -> 105211.25 | H6: =+E6-G6 -> 44068.128 | I6: 74000 | J6: =+K6/G6 -> 0.64631869 | K6: 68000 | L6: =+M6/G6 -> 0.39349402 | M6: 41400 | N6: =+O6/(H6+I6) -> 0.87153071 | O6: 102900 | P6: =+Q6/(H6+I6) -> 0.083849893 | Q6: 9900
A10: Notes:
A11: actual data

Sheet Disb. analysis (MRKT)
A1: Έτος | B1: Νέα πωλήσεις | C1: Finance contribution new | D1: Νέα δάνεια | E1: μέσο ποσό δανείου νέα | F1: Νέα Εκταμιεύσεις (€) | G1: Μτχ πωλήσεις | H1: Finance contribution used | I1: Μτχ δάνεια (k) | J1: μέσο ποσό δανείου Μτχ | K1: Μτχ Εκταμιεύσεις (€) | L1: Σύνολο Εκταμιεύσεις (€)
A2: 2024 | B2: =+'sales analysis (MRKT)'!K2 -> 61000 | C2: =+D2/B2 -> 0.40983607 | D2: 25000 | E2: 15000 | F2: =+E2*D2 -> 375000000 | G2: =+'sales analysis (MRKT)'!O2 -> 96300 | H2: =+I2/G2 -> 0.21806854 | I2: 21000 | J2: 8600 | K2: =+J2*I2 -> 180600000 | L2: =+K2+F2 -> 555600000
A3: 2025 | B3: =+'sales analysis (MRKT)'!K3 -> 63000 | C3: =+C2 -> 0.40983607 | D3: =+C3*B3 -> 25819.672 | E3: =+E2*102% -> 15300 | F3: =+E3*D3 -> 3.9504098e+08 | G3: =+'sales analysis (MRKT)'!O3 -> 98500 | H3: =+H2 -> 0.21806854 | I3: =+H3*G3 -> 21479.751 | J3: 8600 | K3: =+J3*I3 -> 1.8472586e+08 | L3: =+K3+F3 -> 5.7976684e+08
A4: 2026 | B4: =+'sales analysis (MRKT)'!K4 -> 65500 | C4: =+C3 -> 0.40983607 | D4: 30000 | E4: =+E3*102% -> 15606 | F4: =+E4*D4 -> 468180000 | G4: =+'sales analysis (MRKT)'!O4 -> 100700 | H4: =+H3 -> 0.21806854 | I4: =+H4*G4 -> 21959.502 | J4: 8600 | K4: =+J4*I4 -> 1.8885171e+08 | L4: =+K4+F4 -> 6.5703171e+08
A5: 2027 | B5: =+'sales analysis (MRKT)'!K5 -> 68000 | C5: =+C4 -> 0.40983607 | D5: 32000 | E5: =+E4*102% -> 15918.12 | F5: =+E5*D5 -> 509379840 | G5: =+'sales analysis (MRKT)'!O5 -> 102900 | H5: =+H4 -> 0.21806854 | I5: =+H5*G5 -> 22439.252 | J5: 8600 | K5: =+J5*I5 -> 1.9297757e+08 | L5: =+K5+F5 -> 7.0235741e+08
A6: 2028 | B6: =+'sales analysis (MRKT)'!K6 -> 68000 | C6: =+C5 -> 0.40983607 | D6: 34000 | E6: =+E5*102% -> 16236.482 | F6: =+E6*D6 -> 5.520404e+08 | G6: =+'sales analysis (MRKT)'!O6 -> 102900 | H6: =+H5 -> 0.21806854 | I6: =+H6*G6 -> 22439.252 | J6: 8600 | K6: =+J6*I6 -> 1.9297757e+08 | L6: =+K6+F6 -> 7.4501797e+08
A10: Notes:
A11: 2% annual infation

Sheet Disb. analysis (S.Βanks)
A1: Έτος | B1: Νέα Εκταμιεύσεις (€) | C1: Μτχ Εκταμιεύσεις (€) | D1: Σύνολο Εκταμιεύσεις (€) | E1: S. Banks market share | F1: Σύνολο Εκταμιεύσεις (€) S.Banks | G1: Νέα Εκταμιεύσεις (€) | H1: Μτχ Εκταμιεύσεις (€) | I1: Σύνολο Εκταμιεύσεις (€) | J1: S.Banks portion on total market
A2: 2024 | B2: 375000000 | C2: 180600000 | D2: 555600000 | E2: =+F2/D2 -> 0.7649388 | F2: 425000000 | G2: =+F2*(B2/D2) -> 2.8685205e+08 | H2: =+F2*(C2/D2) -> 1.3814795e+08 | I2: =+H2+G2 -> 425000000 | J2: =+I2/'Disb. analysis (MRKT)'!L2 -> 0.7649388
A3: 2025 | B3: 3.9504098e+08 | C3: 1.8472586e+08 | D3: 5.7976684e+08 | E3: =+E2 -> 0.7649388 | F3: =+E3*D3 -> 4.4348615e+08 | G3: =+F3*(B3/D3) -> 3.0218218e+08 | H3: =+F3*(C3/D3) -> 1.4130398e+08 | I3: =+H3+G3 -> 4.4348615e+08 | J3: =+I3/'Disb. analysis (MRKT)'!L3 -> 0.7649388
A4: 2026 | B4: 468180000 | C4: 1.8885171e+08 | D4: 6.5703171e+08 | E4: =+E3 -> 0.7649388 | F4: =+E4*D4 -> 5.0258905e+08 | G4: =+F4*(B4/D4) -> 3.5812905e+08 | H4: =+F4*(C4/D4) -> 1.4446e+08 | I4: =+H4+G4 -> 5.0258905e+08 | J4: =+I4/'Disb. analysis (MRKT)'!L4 -> 0.7649388
A5: 2027 | B5: 509379840 | C5: 1.9297757e+08 | D5: 7.0235741e+08 | E5: =+E4 -> 0.7649388 | F5: =+E5*D5 -> 5.3726044e+08 | G5: =+F5*(B5/D5) -> 3.8964441e+08 | H5: =+F5*(C5/D5) -> 1.4761603e+08 | I5: =+H5+G5 -> 5.3726044e+08 | J5: =+I5/'Disb. analysis (MRKT)'!L5 -> 0.7649388
A6: 2028 | B6: 5.520404e+08 | C6: 1.9297757e+08 | D6: 7.4501797e+08 | E6: =+E5 -> 0.7649388 | F6: =+E6*D6 -> 5.6989316e+08 | G6: =+F6*(B6/D6) -> 4.2227713e+08 | H6: =+F6*(C6/D6) -> 1.4761603e+08 | I6: =+H6+G6 -> 5.6989316e+08 | J6: =+I6/'Disb. analysis (MRKT)'!L6 -> 0.7649388
A10: Notes:

Sheet Disb. analysis (EUROBANK)
A1: Έτος | B1: Εκταμιεύσεις Eurobank new | C1: Εκταμιεύσεις Eurobank used | D1: Market share new total market | E1: Market share used total market | F1: Market share auto total market | G1: Market share new S. Banks market | H1: Market share used S. Banks market | I1: Market share auto S. Banks market
A2: 2024 | B2: 128675000 | C2: 28253000 | D2: =+B2/'Disb. analysis (MRKT)'!F2 -> 0.34313333 | E2: =+C2/'Disb. analysis (MRKT)'!K2 -> 0.15643965 | F2: =+(B2+C2)/'Disb. analysis (MRKT)'!L2 -> 0.2824478 | G2: =+B2/'Disb. analysis (S.Βanks)'!G2 -> 0.44857619 | H2: =+C2/'Disb. analysis (S.Βanks)'!H2 -> 0.20451263 | I2: =+(B2+C2)/'Disb. analysis (S.Βanks)'!I2 -> 0.36924235
A3: 2025 | B3: 119167000 | C3: 21588750 | D3: =+B3/'Disb. analysis (MRKT)'!F3 -> 0.30165731 | E3: =+C3/'Disb. analysis (MRKT)'!K3 -> 0.11686913 | F3: =+(B3+C3)/'Disb. analysis (MRKT)'!L3 -> 0.24277992 | G3: =+B3/'Disb. analysis (S.Βanks)'!G3 -> 0.39435483 | H3: =+C3/'Disb. analysis (S.Βanks)'!H3 -> 0.15278233 | I3: =+(B3+C3)/'Disb. analysis (S.Βanks)'!I3 -> 0.31738477
A4: 2026 | B4: 124500000 | C4: 20400000 | D4: =+B4/'Disb. analysis (MRKT)'!F4 -> 0.26592336 | E4: =+C4/'Disb. analysis (MRKT)'!K4 -> 0.10802126 | F4: =+(B4+C4)/'Disb. analysis (MRKT)'!L4 -> 0.2205373 | G4: =+B4/'Disb. analysis (S.Βanks)'!G4 -> 0.34764005 | H4: =+C4/'Disb. analysis (S.Βanks)'!H4 -> 0.14121556 | I4: =+(B4+C4)/'Disb. analysis (S.Βanks)'!I4 -> 0.28830711
A5: 2027 | B5: 128000000 | C5: 21000000 | D5: =+B5/'Disb. analysis (MRKT)'!F5 -> 0.25128596 | E5: =+C5/'Disb. analysis (MRKT)'!K5 -> 0.10882094 | F5: =+(B5+C5)/'Disb. analysis (MRKT)'!L5 -> 0.2121427 | G5: =+B5/'Disb. analysis (S.Βanks)'!G5 -> 0.32850465 | H5: =+C5/'Disb. analysis (S.Βanks)'!H5 -> 0.14226097 | I5: =+(B5+C5)/'Disb. analysis (S.Βanks)'!I5 -> 0.27733291
A6: 2028 | B6: 130000000 | C6: 23000000 | D6: =+B6/'Disb. analysis (MRKT)'!F6 -> 0.23549001 | E6: =+C6/'Disb. analysis (MRKT)'!K6 -> 0.11918484 | F6: =+(B6+C6)/'Disb. analysis (MRKT)'!L6 -> 0.20536417 | G6: =+B6/'Disb. analysis (S.Βanks)'!G6 -> 0.30785471 | H6: =+C6/'Disb. analysis (S.Βanks)'!H6 -> 0.15580963 | I6: =+(B6+C6)/'Disb. analysis (S.Βanks)'!I6 -> 0.26847138
A10: Notes:
A11: actual data

Sheet B2B financing market
B2: 1. Avg. yearly stock, by segment
D3: 2024 | E3: 2030 | F3: 2030 | J3: 2030
B4: Segment | C4: Car type | D4: Car sold to end customers, yearly | E4: Car sold to end customers, yearly | F4: Car sold to end customers, monthly | G4: Avg. stock Rotation, per year | H4: Avg. Yearly stock, k# | I4: Financing penetration, % | J4: Car volumes financed, k# | K4: Yearly target for retail, % | L4: Yearly target for SB, % | M4: Yearly target for retail, #k | N4: Yearly target for retail, #k | O4: Notes
B5: in k#
A6: =B6&C6 -> DealerNew Auto | B6: Dealer | C6: New Auto | D6: 62 | E6: 74 | F6: =E6/12 -> 6.1666667 | G6: =360/60 -> 6 | H6: =E6/G6 -> 12.333333 | I6: 0.9 | J6: =(E6)*I6 -> 66.6 | K6: 1 | M6: =J6*K6 -> 66.6 | N6: =K6*L6 -> 0 | O6: Assuming stable inventory; stock rotation: 365/days supply
A7: =B7&C7 -> DealerUsed Auto | B7: Dealer | C7: Used Auto | D7: 68 | E7: 90 | F7: =E7/12 -> 7.5 | G7: =365/45 -> 8.1111111 | H7: =E7/G7 -> 11.09589 | I7: 0.9 | J7: =(E7)*I7 -> 81 | K7: 1 | M7: =J7*K7 -> 81 | N7: =K7*L7 -> 0 | O7: Assuming stable inventory; stock rotation: 365/days supply
A8: =B8&C8 -> Independent dealersNew Auto | B8: Independent dealers | C8: New Auto | D8: =85%*D6 -> 52.7 | E8: =85%*E6 -> 62.9 | G8: =360/60 -> 6 | H8: =E8/G8 -> 10.483333 | I8: 0.9 | J8: =(E8)*I8 -> 56.61
A9: =B9&C9 -> Independent dealersUsed Auto | B9: Independent dealers | C9: Used Auto | D9: =85%*D7 -> 57.8 | E9: =85%*E7 -> 76.5 | G9: =365/45 -> 8.1111111 | H9: =E9/G9 -> 9.4315068 | I9: 0.9 | J9: =(E9)*I9 -> 68.85
A10: =B10&C10 -> Dealers with OEMs captivesNew Auto | B10: Dealers with OEMs captives | C10: New Auto | D10: =D6-D8 -> 9.3 | E10: =E6-E8 -> 11.1 | G10: =360/60 -> 6 | H10: =E10/G10 -> 1.85 | I10: 0.9 | J10: =(E10)*I10 -> 9.99
A11: =B11&C11 -> Dealers with OEMs captivesUsed Auto | B11: Dealers with OEMs captives | C11: Used Auto | D11: =D7-D9 -> 10.2 | E11: =E7-E9 -> 13.5 | G11: =365/45 -> 8.1111111 | H11: =E11/G11 -> 1.6643836 | I11: 0.9 | J11: =(E11)*I11 -> 12.15
A12: =B12&C12 -> LeaseCosNew Auto | B12: LeaseCos | C12: New Auto | D12: 45 | E12: 54 | F12: =E12/12 -> 4.5 | I12: 0.85 | J12: =(E12)*I12 -> 45.9 | L12: 0.2 | M12: =J12*K12 -> 0 | N12: =K12*L12 -> 0 | O12: ERB Leasing
A13: =B13&C13 -> LeaseCosUsed Auto | B13: LeaseCos | C13: Used Auto | D13: 0 | E13: 0 | F13: =E13/12 -> 0 | I13: 0.85 | J13: =(E13)*I13 -> 0 | L13: 0.2 | M13: =J13*K13 -> 0 | N13: =K13*L13 -> 0 | O13: ERB Leasing
A14: =B14&C14 -> RACNew Auto | B14: RAC | C14: New Auto | D14: 26 | E14: 31 | F14: =E14/12 -> 2.5833333 | I14: 0.8 | J14: =(E14)*I14 -> 24.8 | L14: 0.3 | M14: =J14*K14 -> 0 | N14: =K14*L14 -> 0
A15: =B15&C15 -> RACUsed Auto | B15: RAC | C15: Used Auto | D15: 14 | E15: 16 | F15: =E15/12 -> 1.3333333 | I15: 0.8 | J15: =(E15)*I15 -> 12.8 | L15: 0.3 | M15: =J15*K15 -> 0 | N15: =K15*L15 -> 0
A16: small | B16: RAC | C16: New Auto | D16: =ROUND(30%*D14,0) -> 8 | F16: =E16/12 -> 0 | G16: =360/30 -> 12 | I16: 0.35 | J16: =(E16)*I16 -> 0 | M16: =J16*K16 -> 0 | N16: =K16*L16 -> 0
A17: small | B17: RAC | C17: Used Auto | D17: =ROUND(30%*D15,0) -> 4 | F17: =E17/12 -> 0 | G17: =360/30 -> 12 | I17: 0.35 | J17: =(E17)*I17 -> 0 | M17: =J17*K17 -> 0 | N17: =K17*L17 -> 0
B18: Direct corp | C18: New Auto | D18: 4 | E18: 4 | F18: =E18/12 -> 0.33333333 | I18: 0.2
B19: Direct corp | C19: Used Auto | D19: 2 | E19: 2 | F19: =E19/12 -> 0.16666667 | I19: 0.2
B20: Total | D20: =SUM(D12:D19) -> 103 | E20: =SUM(E12:E19) -> 107 | F20: =SUM(F12:F19) -> 8.9166667 | H20: =SUM(H6:H19) -> 46.858447 | J20: =SUM(J8:J19) -> 231.1 | M20: =SUM(M12:M19) -> 0 | N20: =SUM(N12:N19) -> 0
B22: 2024 | C22: Customer view | D22: Customer view | E22: Dealer view | F22: Dealer view
B23: Product | C23: New Auto | D23: Used Auto | E23: New Auto | F23: Used Auto | G23: notes
B24: in €
B25: Auto loan | C25: 15000 | D25: 9500 | E25: =C25/(1+30%) -> 11538.462 | F25: =D25/(1+30%) -> 7307.6923 | G25: Considering 30%% markup
B26: Floor plan | C26: 0 | D26: 5000 | E26: =C26/(1+30%) -> 0 | F26: =D26/(1+30%) -> 3846.1538 | G26: Considering 30%% markup
B27: Stock finance
B28: Leasing | C28: 25000 | D28: 13000 | E28: =C28/(1+30%) -> 19230.769 | F28: =D28/(1+30%) -> 10000 | G28: Considering 30%% markup
B29: Other | E29: =C29/(1+30%) -> 0 | F29: =D29/(1+30%) -> 0 | G29: Considering 30%% markup
B31: 2. Product mix, %
C32: 2024
B33: Product | C33: Car type | D33: Segment | G33: Notes
B34: in % | D34: LeaseCos | E34: RAC | F34: Independent dealers | G34: Dealers with OEMs captives
A35: =B35&C35 -> Floor planNew Auto | B35: Floor plan | C35: New Auto | D35: 0 | E35: 0 | F35: 0.4 | G35: 0.7 | H35: Only Toyota, Mercedez and small syngelidis group brands have floor plan (only 1 brand)
A36: =B36&C36 -> Floor planUsed Auto | B36: Floor plan | C36: Used Auto | D36: 0 | E36: 0 | F36: 0 | G36: 0.4
A37: =B37&C37 -> Stock financeNew Auto | B37: Stock finance | C37: New Auto | D37: 0 | E37: 0 | F37: 0.15 | G37: 0.05
A38: =B38&C38 -> Stock financeUsed Auto | B38: Stock finance | C38: Used Auto | D38: 0 | E38: 0 | F38: 0.25 | G38: 0.05
A39: =B39&C39 -> LoanNew Auto | B39: Loan | C39: New Auto | D39: 0.3 | E39: 0.25 | F39: 0.15 | G39: 0.05
A40: =B40&C40 -> LoanUsed Auto | B40: Loan | C40: Used Auto | D40: 0 | E40: 0.4 | F40: 0.4 | G40: 0.3
A41: =B41&C41 -> Financial leaseNew Auto | B41: Financial lease | C41: New Auto | D41: 0.6 | E41: 0.5 | F41: 0.15 | G41: 0
A42: =B42&C42 -> Financial leaseUsed Auto | B42: Financial lease | C42: Used Auto | D42: 0 | E42: 0.2 | F42: 0 | G42: 0
A43: =B43&C43 -> Operational leaseNew Auto | B43: Operational lease | C43: New Auto | D43: 0 | E43: 0 | F43: 0 | G43: 0
A44: =B44&C44 -> Operational leaseUsed Auto | B44: Operational lease | C44: Used Auto | D44: 0 | E44: 0 | F44: 0 | G44: 0
A45: =B45&C45 -> Other fin productsNew Auto | B45: Other fin products | C45: New Auto | D45: 0.1 | E45: 0.25 | F45: 0.15 | G45: 0.2 | H45: e.g., RRF
A46: =B46&C46 -> Other fin productsUsed Auto | B46: Other fin products | C46: Used Auto | D46: 0 | E46: 0.4 | F46: 0.35 | G46: 0.25 | H46: e.g., RRF
B47: Total | C47: New Auto | D47: =SUMIFS(D$35:D$46,$C$35:$C$46,$C47) -> 1 | E47: =SUMIFS(E$35:E$46,$C$35:$C$46,$C47) -> 1 | F47: =SUMIFS(F$35:F$46,$C$35:$C$46,$C47) -> 1 | G47: =SUMIFS(G$35:G$46,$C$35:$C$46,$C47) -> 1
B48: Total | C48: Used Auto | D48: =SUMIFS(D$35:D$46,$C$35:$C$46,$C48) -> 0 | E48: =SUMIFS(E$35:E$46,$C$35:$C$46,$C48) -> 1 | F48: =SUMIFS(F$35:F$46,$C$35:$C$46,$C48) -> 1 | G48: =SUMIFS(G$35:G$46,$C$35:$C$46,$C48) -> 1
B50: 3. RAR per contract
C51: 2024 | E51: 2030 | F51: 2030
B52: Pricing component | C52: Auto loan | E52: Auto loan | G52: Floor plan | I52: Stock finance
B53: in € | C53: New Auto | D53: Used Auto | E53: New Auto | F53: Used Auto | G53: New Auto | H53: Used Auto | I53: New Auto | J53: Used Auto
B55: Average loan amount | C55: 15000 | D55: 9500 | E55: 17395.401 | F55: 11017.087
B56: Average rate | C56: 0.078 | D56: 0.117 | E56: 0.078 | F56: 0.117 | G56: 0.078 | H56: 0.117 | I56: 0.078 | J56: 0.117
B57: Average cost of fund | C57: 0.039 | D57: 0.04 | E57: 0.039 | F57: 0.04 | G57: 0.039 | H57: 0.04 | I57: 0.039 | J57: 0.04
B58: Average cost of risk | C58: 0.008 | D58: 0.009 | E58: 0.008 | F58: 0.009 | G58: 0.008 | H58: 0.009 | I58: 0.008 | J58: 0.009
B59: Average contract duration | C59: =4.22222222222222 -> 4.2222222 | D59: =4.22222222222222 -> 4.2222222 | E59: =4.22222222222222 -> 4.2222222 | F59: =4.22222222222222 -> 4.2222222 | G59: =90/360 -> 0.25 | H59: =90/360 -> 0.25
B60: Total RAR per car | C60: =C61/C59 -> 232.5 | D60: =D61/D59 -> 323 | E60: =E61/E59 -> 269.62872 | F60: =F61/F59 -> 374.58097 | G60: =G61/G59 -> 0 | H60: =H61/H59 -> 0 | I60: =I61/I59 -> #DIV/0! | J60: =J61/J59 -> #DIV/0!
B61: Total RAR per contract | C61: =C55*(C56-C57-C58)*C59/2 -> 981.66667 | D61: =D55*(D56-D57-D58)*D59/2 -> 1363.7778 | E61: =E55*(E56-E57-E58)*E59/2 -> 1138.4324 | F61: =F55*(F56-F57-F58)*F59/2 -> 1581.5641 | G61: =G55*(G56-G57-G58)*G59/2 -> 0 | H61: =H55*(H56-H57-H58)*H59/2 -> 0 | I61: =I55*(I56-I57-I58)*I59/2 -> 0 | J61: =J55*(J56-J57-J58)*J59/2 -> 0
C63: 2024
B64: Pricing component | C64: Operating lease
B65: in € | C65: New Auto | D65: Used Auto
B66: Leasing RAR | C66: 375 | D66: 200
B67: Services RAR | C67: 375 | D67: 200
B68: UCS RAR | C68: 250 | D68: 150
B69: Average contract duration | C69: 3.5 | D69: 3.5
B70: Total RAR per car | C70: =SUM(C66:C68) -> 1000 | D70: =SUM(D66:D68) -> 550
B71: Total RAR per contract | C71: =C70*C69 -> 3500 | D71: =D70*D69 -> 1925
B73: 4. Total RAR for the B2B market
C74: 2024 | D74: Avg. Yearly stock, k#
B75: Product | C75: Car type | D75: LeaseCos | E75: RAC | F75: Independent dealers | G75: Dealers with OEMs captives | I75: Avg. Yearly stock, k# | J75: Financing penetration, % | K75: Car volumes financed, k# | L75: Yearly target for retail, % | M75: Yearly target for retail, #k | N75: Notes
B76: Number of cars financed, #
B77: Floor plan | C77: New Auto | D77: =INDEX($A$34:$G$46,MATCH($B77&$C77,$A$34:$A$46,0),MATCH(D$75,$A$34:$G$34,0))*_xlfn.XLOOKUP(D$75&$C77,$A$6:$A$15,$J$6:$J$15,0,0) -> 0 | E77: =INDEX($A$34:$G$46,MATCH($B77&$C77,$A$34:$A$46,0),MATCH(E$75,$A$34:$G$34,0))*_xlfn.XLOOKUP(E$75&$C77,$A$6:$A$15,$J$6:$J$15,0,0) -> 0 | F77: =INDEX($A$34:$G$46,MATCH($B77&$C77,$A$34:$A$46,0),MATCH(F$75,$A$34:$G$34,0))*_xlfn.XLOOKUP(F$75&$C77,$A$6:$A$15,$J$6:$J$15,0,0) -> 22.644 | G77: =INDEX($A$34:$G$46,MATCH($B77&$C77,$A$34:$A$46,0),MATCH(G$75,$A$34:$G$34,0))*_xlfn.XLOOKUP(G$75&$C77,$A$6:$A$15,$J$6:$J$15,0,0) -> 6.993 | N77: ERB Leasing
B78: Floor plan | C78: Used Auto | D78: =INDEX($A$34:$G$46,MATCH($B78&$C78,$A$34:$A$46,0),MATCH(D$75,$A$34:$G$34,0))*_xlfn.XLOOKUP(D$75&$C78,$A$6:$A$15,$J$6:$J$15,0,0) -> 0 | E78: =INDEX($A$34:$G$46,MATCH($B78&$C78,$A$34:$A$46,0),MATCH(E$75,$A$34:$G$34,0))*_xlfn.XLOOKUP(E$75&$C78,$A$6:$A$15,$J$6:$J$15,0,0) -> 0 | F78: =INDEX($A$34:$G$46,MATCH($B78&$C78,$A$34:$A$46,0),MATCH(F$75,$A$34:$G$34,0))*_xlfn.XLOOKUP(F$75&$C78,$A$6:$A$15,$J$6:$J$15,0,0) -> 0 | G78: =INDEX($A$34:$G$46,MATCH($B78&$C78,$A$34:$A$46,0),MATCH(G$75,$A$34:$G$34,0))*_xlfn.XLOOKUP(G$75&$C78,$A$6:$A$15,$J$6:$J$15,0,0) -> 4.86 | N78: ERB Leasing
B79: Stock finance | C79: New Auto | D79: =INDEX($A$34:$G$46,MATCH($B79&$C79,$A$34:$A$46,0),MATCH(D$75,$A$34:$G$34,0))*_xlfn.XLOOKUP(D$75&$C79,$A$6:$A$15,$J$6:$J$15,0,0) -> 0 | E79: =INDEX($A$34:$G$46,MATCH($B79&$C79,$A$34:$A$46,0),MATCH(E$75,$A$34:$G$34,0))*_xlfn.XLOOKUP(E$75&$C79,$A$6:$A$15,$J$6:$J$15,0,0) -> 0 | F79: =INDEX($A$34:$G$46,MATCH($B79&$C79,$A$34:$A$46,0),MATCH(F$75,$A$34:$G$34,0))*_xlfn.XLOOKUP(F$75&$C79,$A$6:$A$15,$J$6:$J$15,0,0) -> 8.4915 | G79: =INDEX($A$34:$G$46,MATCH($B79&$C79,$A$34:$A$46,0),MATCH(G$75,$A$34:$G$34,0))*_xlfn.XLOOKUP(G$75&$C79,$A$6:$A$15,$J$6:$J$15,0,0) -> 0.4995
B80: Stock finance | C80: Used Auto | D80: =INDEX($A$34:$G$46,MATCH($B80&$C80,$A$34:$A$46,0),MATCH(D$75,$A$34:$G$34,0))*_xlfn.XLOOKUP(D$75&$C80,$A$6:$A$15,$J$6:$J$15,0,0) -> 0 | E80: =INDEX($A$34:$G$46,MATCH($B80&$C80,$A$34:$A$46,0),MATCH(E$75,$A$34:$G$34,0))*_xlfn.XLOOKUP(E$75&$C80,$A$6:$A$15,$J$6:$J$15,0,0) -> 0 | F80: =INDEX($A$34:$G$46,MATCH($B80&$C80,$A$34:$A$46,0),MATCH(F$75,$A$34:$G$34,0))*_xlfn.XLOOKUP(F$75&$C80,$A$6:$A$15,$J$6:$J$15,0,0) -> 17.2125 | G80: =INDEX($A$34:$G$46,MATCH($B80&$C80,$A$34:$A$46,0),MATCH(G$75,$A$34:$G$34,0))*_xlfn.XLOOKUP(G$75&$C80,$A$6:$A$15,$J$6:$J$15,0,0) -> 0.6075
B81: Loan | C81: New Auto | D81: =INDEX($A$34:$G$46,MATCH($B81&$C81,$A$34:$A$46,0),MATCH(D$75,$A$34:$G$34,0))*_xlfn.XLOOKUP(D$75&$C81,$A$6:$A$15,$J$6:$J$15,0,0) -> 13.77 | E81: =INDEX($A$34:$G$46,MATCH($B81&$C81,$A$34:$A$46,0),MATCH(E$75,$A$34:$G$34,0))*_xlfn.XLOOKUP(E$75&$C81,$A$6:$A$15,$J$6:$J$15,0,0) -> 6.2 | F81: =INDEX($A$34:$G$46,MATCH($B81&$C81,$A$34:$A$46,0),MATCH(F$75,$A$34:$G$34,0))*_xlfn.XLOOKUP(F$75&$C81,$A$6:$A$15,$J$6:$J$15,0,0) -> 8.4915 | G81: =INDEX($A$34:$G$46,MATCH($B81&$C81,$A$34:$A$46,0),MATCH(G$75,$A$34:$G$34,0))*_xlfn.XLOOKUP(G$75&$C81,$A$6:$A$15,$J$6:$J$15,0,0) -> 0.4995
B82: Loan | C82: Used Auto | D82: =INDEX($A$34:$G$46,MATCH($B82&$C82,$A$34:$A$46,0),MATCH(D$75,$A$34:$G$34,0))*_xlfn.XLOOKUP(D$75&$C82,$A$6:$A$15,$J$6:$J$15,0,0) -> 0 | E82: =INDEX($A$34:$G$46,MATCH($B82&$C82,$A$34:$A$46,0),MATCH(E$75,$A$34:$G$34,0))*_xlfn.XLOOKUP(E$75&$C82,$A$6:$A$15,$J$6:$J$15,0,0) -> 5.12 | F82: =INDEX($A$34:$G$46,MATCH($B82&$C82,$A$34:$A$46,0),MATCH(F$75,$A$34:$G$34,0))*_xlfn.XLOOKUP(F$75&$C82,$A$6:$A$15,$J$6:$J$15,0,0) -> 27.54 | G82: =INDEX($A$34:$G$46,MATCH($B82&$C82,$A$34:$A$46,0),MATCH(G$75,$A$34:$G$34,0))*_xlfn.XLOOKUP(G$75&$C82,$A$6:$A$15,$J$6:$J$15,0,0) -> 3.645
B83: Financial lease | C83: New Auto | D83: =INDEX($A$34:$G$46,MATCH($B83&$C83,$A$34:$A$46,0),MATCH(D$75,$A$34:$G$34,0))*_xlfn.XLOOKUP(D$75&$C83,$A$6:$A$15,$J$6:$J$15,0,0) -> 27.54 | E83: =INDEX($A$34:$G$46,MATCH($B83&$C83,$A$34:$A$46,0),MATCH(E$75,$A$34:$G$34,0))*_xlfn.XLOOKUP(E$75&$C83,$A$6:$A$15,$J$6:$J$15,0,0) -> 12.4 | F83: =INDEX($A$34:$G$46,MATCH($B83&$C83,$A$34:$A$46,0),MATCH(F$75,$A$34:$G$34,0))*_xlfn.XLOOKUP(F$75&$C83,$A$6:$A$15,$J$6:$J$15,0,0) -> 8.4915 | G83: =INDEX($A$34:$G$46,MATCH($B83&$C83,$A$34:$A$46,0),MATCH(G$75,$A$34:$G$34,0))*_xlfn.XLOOKUP(G$75&$C83,$A$6:$A$15,$J$6:$J$15,0,0) -> 0
B84: Financial lease | C84: Used Auto | D84: =INDEX($A$34:$G$46,MATCH($B84&$C84,$A$34:$A$46,0),MATCH(D$75,$A$34:$G$34,0))*_xlfn.XLOOKUP(D$75&$C84,$A$6:$A$15,$J$6:$J$15,0,0) -> 0 | E84: =INDEX($A$34:$G$46,MATCH($B84&$C84,$A$34:$A$46,0),MATCH(E$75,$A$34:$G$34,0))*_xlfn.XLOOKUP(E$75&$C84,$A$6:$A$15,$J$6:$J$15,0,0) -> 2.56 | F84: =INDEX($A$34:$G$46,MATCH($B84&$C84,$A$34:$A$46,0),MATCH(F$75,$A$34:$G$34,0))*_xlfn.XLOOKUP(F$75&$C84,$A$6:$A$15,$J$6:$J$15,0,0) -> 0 | G84: =INDEX($A$34:$G$46,MATCH($B84&$C84,$A$34:$A$46,0),MATCH(G$75,$A$34:$G$34,0))*_xlfn.XLOOKUP(G$75&$C84,$A$6:$A$15,$J$6:$J$15,0,0) -> 0
B85: Operational lease | C85: New Auto | D85: =INDEX($A$34:$G$46,MATCH($B85&$C85,$A$34:$A$46,0),MATCH(D$75,$A$34:$G$34,0))*_xlfn.XLOOKUP(D$75&$C85,$A$6:$A$15,$J$6:$J$15,0,0) -> 0 | E85: =INDEX($A$34:$G$46,MATCH($B85&$C85,$A$34:$A$46,0),MATCH(E$75,$A$34:$G$34,0))*_xlfn.XLOOKUP(E$75&$C85,$A$6:$A$15,$J$6:$J$15,0,0) -> 0 | F85: =INDEX($A$34:$G$46,MATCH($B85&$C85,$A$34:$A$46,0),MATCH(F$75,$A$34:$G$34,0))*_xlfn.XLOOKUP(F$75&$C85,$A$6:$A$15,$J$6:$J$15,0,0) -> 0 | G85: =INDEX($A$34:$G$46,MATCH($B85&$C85,$A$34:$A$46,0),MATCH(G$75,$A$34:$G$34,0))*_xlfn.XLOOKUP(G$75&$C85,$A$6:$A$15,$J$6:$J$15,0,0) -> 0
B86: Operational lease | C86: Used Auto | D86: =INDEX($A$34:$G$46,MATCH($B86&$C86,$A$34:$A$46,0),MATCH(D$75,$A$34:$G$34,0))*_xlfn.XLOOKUP(D$75&$C86,$A$6:$A$15,$J$6:$J$15,0,0) -> 0 | E86: =INDEX($A$34:$G$46,MATCH($B86&$C86,$A$34:$A$46,0),MATCH(E$75,$A$34:$G$34,0))*_xlfn.XLOOKUP(E$75&$C86,$A$6:$A$15,$J$6:$J$15,0,0) -> 0 | F86: =INDEX($A$34:$G$46,MATCH($B86&$C86,$A$34:$A$46,0),MATCH(F$75,$A$34:$G$34,0))*_xlfn.XLOOKUP(F$75&$C86,$A$6:$A$15,$J$6:$J$15,0,0) -> 0 | G86: =INDEX($A$34:$G$46,MATCH($B86&$C86,$A$34:$A$46,0),MATCH(G$75,$A$34:$G$34,0))*_xlfn.XLOOKUP(G$75&$C86,$A$6:$A$15,$J$6:$J$15,0,0) -> 0
B87: Other fin products | C87: New Auto | D87: =INDEX($A$34:$G$46,MATCH($B87&$C87,$A$34:$A$46,0),MATCH(D$75,$A$34:$G$34,0))*_xlfn.XLOOKUP(D$75&$C87,$A$6:$A$15,$J$6:$J$15,0,0) -> 4.59 | E87: =INDEX($A$34:$G$46,MATCH($B87&$C87,$A$34:$A$46,0),MATCH(E$75,$A$34:$G$34,0))*_xlfn.XLOOKUP(E$75&$C87,$A$6:$A$15,$J$6:$J$15,0,0) -> 6.2 | F87: =INDEX($A$34:$G$46,MATCH($B87&$C87,$A$34:$A$46,0),MATCH(F$75,$A$34:$G$34,0))*_xlfn.XLOOKUP(F$75&$C87,$A$6:$A$15,$J$6:$J$15,0,0) -> 8.4915 | G87: =INDEX($A$34:$G$46,MATCH($B87&$C87,$A$34:$A$46,0),MATCH(G$75,$A$34:$G$34,0))*_xlfn.XLOOKUP(G$75&$C87,$A$6:$A$15,$J$6:$J$15,0,0) -> 1.998
B88: Other fin products | C88: Used Auto | D88: =INDEX($A$34:$G$46,MATCH($B88&$C88,$A$34:$A$46,0),MATCH(D$75,$A$34:$G$34,0))*_xlfn.XLOOKUP(D$75&$C88,$A$6:$A$15,$J$6:$J$15,0,0) -> 0 | E88: =INDEX($A$34:$G$46,MATCH($B88&$C88,$A$34:$A$46,0),MATCH(E$75,$A$34:$G$34,0))*_xlfn.XLOOKUP(E$75&$C88,$A$6:$A$15,$J$6:$J$15,0,0) -> 5.12 | F88: =INDEX($A$34:$G$46,MATCH($B88&$C88,$A$34:$A$46,0),MATCH(F$75,$A$34:$G$34,0))*_xlfn.XLOOKUP(F$75&$C88,$A$6:$A$15,$J$6:$J$15,0,0) -> 24.0975 | G88: =INDEX($A$34:$G$46,MATCH($B88&$C88,$A$34:$A$46,0),MATCH(G$75,$A$34:$G$34,0))*_xlfn.XLOOKUP(G$75&$C88,$A$6:$A$15,$J$6:$J$15,0,0) -> 3.0375
B89: Total | C89: New Auto | D89: =SUMIFS(D$77:D$88,$C$77:$C$88,$C89) -> 45.9 | E89: =SUMIFS(E$77:E$88,$C$77:$C$88,$C89) -> 24.8 | F89: =SUMIFS(F$77:F$88,$C$77:$C$88,$C89) -> 56.61 | G89: =SUMIFS(G$77:G$88,$C$77:$C$88,$C89) -> 9.99
B90: Total | C90: Used Auto | D90: =SUMIFS(D$77:D$88,$C$77:$C$88,$C90) -> 0 | E90: =SUMIFS(E$77:E$88,$C$77:$C$88,$C90) -> 12.8 | F90: =SUMIFS(F$77:F$88,$C$77:$C$88,$C90) -> 68.85 | G90: =SUMIFS(G$77:G$88,$C$77:$C$88,$C90) -> 12.15

Sheet B2B financing opportunity
B2: B2B Financing Opportunities: Target Wholesalers for Eurobank by 2030
B4: Product | C4: Importer | D4: Number of dealers | E4: Yearly number of cars sold | F4: Total line value | G4: Yearly cars financed | H4: Avg. Car value | I4: RAR per car | J4: Annual RAR | K4: Assumption for selecting the importer | L4: Notes
B5: Unit of measure | D5: # | E5: # | F5: €M | G5: # | H5: € | I5: € | J5: €
B6: Floor plan | C6: Toyota | D6: 20 | F6: 15
B7: Floor plan
B8: Floor plan
B9: Floor plan
B10: Floor plan
B11: Floor plan
B12: Floor plan
B13: Floor plan
B14: Floor plan
B15: Floor plan
B16: Floor plan
B17: Floor plan
B18: Floor plan
... B20: Floor plan
B23: Product | C23: Dealer Group | D23: Number of dealers | E23: Yearly number of cars sold | F23: Total line value | G23: Yearly cars financed | H23: Avg. Car value | I23: RAR per car | J23: Annual RAR | K23: Assumption for selecting the dealer | L23: Notes
B24: Unit of measure | D24: # | E24: # | F24: €M | G24: # | H24: € | I24: € | J24: €
B25: Stock finance
B26: Stock finance
B27: Stock finance
B28: Stock finance
B29: Stock finance
B30: Stock finance
B31: Stock finance
B32: Stock finance
B33: Stock finance
B34: Stock finance
B35: Stock finance
B36: Stock finance
... B39: Stock finance
B43: Product | C43: Fleet Group | D43: Number of dealers | E43: Yearly number of cars sold | F43: Total line value | G43: Yearly cars financed | H43: Avg. Car value | I43: RAR per car | J43: Annual RAR | K43: Assumption for selecting the dealer | L43: Notes
B44: Unit of measure | D44: # | E44: # | F44: €M | G44: # | H44: € | I44: € | J44: €
B45: Fleet financing
B46: Fleet financing
B47: Fleet financing
B48: Fleet financing
B49: Fleet financing
B50: Fleet financing
B51: Fleet financing
B52: Fleet financing
B53: Fleet financing
B54: Fleet financing
B55: Fleet financing
B56: Fleet financing
... B58: Fleet financing
