Workbook

Sheet 2024 business case
B1: Repossession business case
B3: 1. Example parameters
B5: Initial market price of car, € | C5: 30000
B6: Time of default post-contract, years | C6: 2
B8: 2. RV estimation
B10: Car type | C10: Car age at repayment | D10: Avg. car age at origination | E10: Product | F10: # cars for ERB (assuming 2-year fleet) | G10: Bad rate (2023) - assuming no release of credit policy | H10: # expected cars for ERB with bad rates | I10: Repossession penetration | J10: # cars repossessed by ERB | K10: Time at default | L10: Time to repossess | M10: Time when repossessed | N10: RV ratio at repossession | O10: RV at repossession | P10: Expected repossession costs per car | Q10: RV, incl. repossession costs and repossession penetration | R10: RV ratio, incl. repossession costs and repossession penetration
C11: years | D11: years | F11: #k | G11: % | H11: # | I11: % | J11: # | K11: years | L11: months | M11: years | N11: % | O11: € | P11: € | Q11: € | R11: %
B12: New cars | C12: <= 4 | D12: 0 | E12: Loan | F12: 20 | G12: 0.012 | H12: =F12*G12*1000 -> 240 | I12: 0.85 | J12: =I12*H12 -> 204 | K12: =D12+$C$6 -> 2 | L12: 10 | M12: =ROUND(K12+L12/12, 0) -> 3 | N12: =1+HLOOKUP("Y"&M12,$E$39:$S$40, 2, FALSE) -> 0.70526661 | O12: =N12*$C$5 -> 21157.998 | P12: =INDEX('2024 business case'!$C$24:$C$25, MATCH($E12, '2024 business case'!$B$24:$B$25,0))+INDEX('2024 business case'!$D$24:$D$25, MATCH($E12, '2024 business case'!$B$24:$B$25,0))*$O12 -> 2452.8999 | Q12: =O12*I12-P12 -> 15531.399 | R12: =Q12/$C$5 -> 0.51771328
B13: New cars | C13: <= 4 | D13: 0 | E13: Leasing | F13: 0 | G13: =G12 -> 0.012 | H13: =F13*G13*1000 -> 0 | I13: 1 | J13: =I13*H13 -> 0 | K13: =D13+$C$6 -> 2 | L13: 1 | M13: =ROUND(K13+L13/12, 0) -> 2 | N13: =1+HLOOKUP("Y"&M13,$E$39:$S$40, 2, FALSE) -> 0.79183012 | O13: =N13*$C$5 -> 23754.904 | P13: =INDEX('2024 business case'!$C$24:$C$25, MATCH($E13, '2024 business case'!$B$24:$B$25,0))+INDEX('2024 business case'!$D$24:$D$25, MATCH($E13, '2024 business case'!$B$24:$B$25,0))*$O13 -> 1907.7452 | Q13: =O13*I13-P13 -> 21847.158 | R13: =Q13/$C$5 -> 0.72823861
B14: Used cars | C14: <=9 | D14: 3 | E14: Loan | F14: 2.1 | G14: 0.008 | H14: =F14*G14*1000 -> 16.8 | I14: 0.85 | J14: =I14*H14 -> 14.28 | K14: =D14+$C$6 -> 5 | L14: 10 | M14: =ROUND(K14+L14/12, 0) -> 6 | N14: =1+HLOOKUP("Y"&M14,$E$39:$S$40, 2, FALSE) -> 0.51907502 | O14: =N14*$C$5 -> 15572.251 | P14: =INDEX('2024 business case'!$C$24:$C$25, MATCH($E14, '2024 business case'!$B$24:$B$25,0))+INDEX('2024 business case'!$D$24:$D$25, MATCH($E14, '2024 business case'!$B$24:$B$25,0))*$O14 -> 2173.6125 | Q14: =O14*I14-P14 -> 11062.8 | R14: =Q14/$C$5 -> 0.36876002
B15: Used cars | C15: <=9 | D15: 3 | E15: Leasing | F15: 0 | G15: =G14 -> 0.008 | H15: =F15*G15*1000 -> 0 | I15: 1 | J15: =I15*H15 -> 0 | K15: =D15+$C$6 -> 5 | L15: 1 | M15: =ROUND(K15+L15/12, 0) -> 5 | N15: =1+HLOOKUP("Y"&M15,$E$39:$S$40, 2, FALSE) -> 0.57089112 | O15: =N15*$C$5 -> 17126.734 | P15: =INDEX('2024 business case'!$C$24:$C$25, MATCH($E15, '2024 business case'!$B$24:$B$25,0))+INDEX('2024 business case'!$D$24:$D$25, MATCH($E15, '2024 business case'!$B$24:$B$25,0))*$O15 -> 1576.3367 | Q15: =O15*I15-P15 -> 15550.397 | R15: =Q15/$C$5 -> 0.51834657 | T15: Average RV used cars
B16: Used cars | C16: 9-12 | D16: 6 | E16: Loan | F16: 2.7 | G16: 0.036 | H16: =F16*G16*1000 -> 97.2 | I16: 0.85 | J16: =I16*H16 -> 82.62 | K16: =D16+$C$6 -> 8 | L16: 10 | M16: =ROUND(K16+L16/12, 0) -> 9 | N16: =1+HLOOKUP("Y"&M16,$E$39:$S$40, 2, FALSE) -> 0.40108844 | O16: =N16*$C$5 -> 12032.653 | P16: =INDEX('2024 business case'!$C$24:$C$25, MATCH($E16, '2024 business case'!$B$24:$B$25,0))+INDEX('2024 business case'!$D$24:$D$25, MATCH($E16, '2024 business case'!$B$24:$B$25,0))*$O16 -> 1996.6327 | Q16: =O16*I16-P16 -> 8231.1225 | R16: =Q16/$C$5 -> 0.27437075 | T16: =SUMPRODUCT(R14:R17,F14:F17)/SUM(F14:F17) -> 0.29079301
B17: Used cars | C17: >12 | D17: 9 | E17: Loan | F17: 1.2 | G17: 0.028 | H17: =F17*G17*1000 -> 33.6 | I17: 0.85 | J17: =I17*H17 -> 28.56 | K17: =D17+$C$6 -> 11 | L17: 10 | M17: =ROUND(K17+L17/12, 0) -> 12 | N17: =1+HLOOKUP("Y"&M17,$E$39:$S$40, 2, FALSE) -> 0.29725104 | O17: =N17*$C$5 -> 8917.5313 | P17: =INDEX('2024 business case'!$C$24:$C$25, MATCH($E17, '2024 business case'!$B$24:$B$25,0))+INDEX('2024 business case'!$D$24:$D$25, MATCH($E17, '2024 business case'!$B$24:$B$25,0))*$O17 -> 1840.8766 | Q17: =O17*I17-P17 -> 5739.025 | R17: =Q17/$C$5 -> 0.19130083
B18: Total | F18: =SUM(F12:F17) -> 26 | H18: =SUM(H12:H17) -> 387.6 | J18: =SUM(J12:J17) -> 329.46
B20: 3. Unit economics
M21: =SUMPRODUCT(M14:M17,F14:F17)/SUM(F14:F17) -> 8.55
B22: Product | C22: Expected repossession costs per car, excl. remarketing | D22: Expected remarketing costs
B23: Average | C23: € | D23: % of RV
B24: Leasing | C24: =AVERAGE(D33:E33) -> 720 | D24: =AVERAGE(D34:E34) -> 0.05
B25: Loan | C25: =AVERAGE(F33:G33) -> 1395 | D25: =AVERAGE(F34:G34) -> 0.05
B27: Value chain step | C27: Cost type | D27: Leasing | F27: Loan
B28: per car data | C28: € (% of RV for remarketing) | D28: Lower bound | E28: Upper bound | F28: Lower bound | G28: Upper bound
B29: Legal repossession | C29: Commission to repossession agent | D29: 200 | E29: 350 | F29: 900 | G29: 1000
B30: Asset recovery | C30: Fixed fee pre-negotiated with repossession agent depending on car location | D30: 150 | E30: 300 | F30: 150 | G30: 300
B31: Storage | C31: Rent for outdoor lot with surveillance for ~60-90 days | D31: 40 | E31: 50 | F31: 40 | G31: 50
B32: Inspection | C32: Fixed fee pre-negotiated with de-fleeting company for inspection and market value estimation | D32: 150 | E32: 200 | F32: 150 | G32: 200
B33: Expected repossession costs per car, excl. remarketing | D33: =SUM(D29:D32) -> 540 | E33: =SUM(E29:E32) -> 900 | F33: =SUM(F29:F32) -> 1240 | G33: =SUM(G29:G32) -> 1550
B34: Remarketing | C34: Marketplace or dealer commission for car resale (higher for dealer) | D34: 0.02 | E34: 0.08 | F34: 0.02 | G34: 0.08
B35: Expected remarketing costs | D35: =SUM(D34) -> 0.02 | E35: =SUM(E34) -> 0.08 | F35: =SUM(F34) -> 0.02 | G35: =SUM(G34) -> 0.08
B37: 4. Depreciation rates
B39: Make | C39: Model | D39: Market Price | E39: Y1 | F39: Y2 | G39: Y3 | H39: Y4 | I39: Y5 | J39: Y6 | K39: Y7 | L39: Y8 | M39: Y9 | N39: Y10 | O39: Y11 | P39: Y12 | Q39: Y13 | R39: Y14 | S39: Y15
E40: -0.11779974 | F40: -0.20816988 | G40: -0.29473339 | H40: -0.36771237 | I40: -0.42910888 | J40: -0.48092498 | K40: -0.52516275 | L40: -0.56382426 | M40: -0.59891156 | N40: -0.63242673 | O40: -0.66637184 | P40: -0.70274896 | Q40: -0.74356014 | R40: -0.79080747 | S40: -0.846493

Sheet Used car CoR
B2: Scenario A: Eurobank does not develop repossession capabilities
B3: Initiative: | D3: (1) No initiative | E3: (2) Introduction of AA models | F3: (3) Evolve Bank's risk appetite | G3: Owner
B4: Metrics | C4: Applications disbursed, % | D4: 0.37 | E4: 0.45 | F4: =100%-F5-F6-F7 -> 0.58 | G4: Credit policy
C5: Applications Approved & Cancelled, % | D5: 0.05 | E5: 0.07 | F5: 0.07 | G5: Credit policy | H5: not necessary
C6: Applications Counteroffer & Cancelled, % | D6: 0.25 | E6: 0.18 | F6: 0.15 | G6: Credit policy
C7: Applications Rejected, % | D7: 0.33 | E7: 0.3 | F7: 0.2 | G7: Credit policy
C8: Bad rates, % | D8: 0.026 | E8: =((D4*D8)+(E4-D4)*(D8*2))/E4 -> 0.030622222 | F8: 0.048 | G8: Credit policy
C9: Cost of Risk, % | D9: 0.016 | E9: =(D9*E8)/D8 -> 0.018844444 | F9: =F8*D9/D8 -> 0.029538462 | G9: Credit policy | H9: =D9/D8 -> 0.61538462
C10: RAR, €M | D10: 4 | E10: 8 | G10: Business | H10: LGL
C11: Financing disbursements, €M | G11: Business
B13: Scenario B: Eurobank develops repossession capabilities
B14: Initiative: | D14: (1) No initiative | E14: (2) Introduction of AA models | F14: (3) Evolve Bank's risk appetite | G14: Owner
B15: Metrics | C15: Applications disbursed, % | D15: 0.37 | E15: 0.45 | F15: =F4 -> 0.58 | G15: Credit policy
C16: Applications Approved & Cancelled, % | D16: 0.05 | E16: 0.07 | F16: =F5 -> 0.07 | G16: Credit policy
C17: Applications Counteroffer & Cancelled, % | D17: 0.25 | E17: 0.18 | F17: =F6 -> 0.15 | G17: Credit policy
C18: Applications Rejected, % | D18: 0.33 | E18: 0.3 | F18: =F7 -> 0.2 | G18: Credit policy
C19: Bad rates, % | D19: 0.026 | E19: 0.031 | F19: =F8 -> 0.048 | G19: Credit policy
C20: Cost of Risk, % | D20: =D19*H22 -> 0.008434 | E20: =E19*H22 -> 0.010055923 | F20: =F19*H22 -> 0.015570462 | G20: Credit policy | H20: NEW ESTIMATED LGL based on RV 34% as calculated in total from excel "Repossesion Business Case"
C21: Car residual value, % | D21: 0.291 | E21: 0.291 | F21: 0.291 | G21: Business
C22: RAR, €M | G22: Business | H22: =H9-29.1% -> 0.32438462
C23: Financing disbursements, €M | G23: Business
