Workbook

Sheet Executive Summary
B2: Could we increase the risk appetite?
A4: 1 | B4: Reward vs Risk: The risk reward ratio is positively inclined towards reward.
A5: 2 | B5: Break-Even Analysis: A 10% increase in CoR can be offset by a production increase of only ~5%.
A6: 3 | B6: Market Opportunity: The Used Auto market is generally more price-sensitive, therefore more receptive to credit expansion, and can offer rapid volume growth.
A7: 4 | B7: Profitability Resilience: Used Auto maintains high profit margins even with a slightly higher probability of default.

Sheet Inputs
A1: Parameter | B1: Value
A2: Average Loan ticket (€) | B2: 8000

Sheet Summary (actuals)
A1: MOB | B1: New_Auto_CoR_2022 | C1: Used_Auto_CoR_2022 | D1: New_Auto_Profit_2022 | E1: Used_Auto_Profit_2022 | F1: Διαφορά_CoR (Used - New) | G1: Diff_Profit (Used - New) | I1: Risk-Reward Ratio
A2: 6 | B2: -1.4 | C2: -2.4 | D2: 2.7 | E2: 4.3 | F2: =+C2-B2 -> -1 | G2: =+E2-D2 -> 1.6 | I2: =-C2/E2 -> 0.55813953
A3: 12 | B3: -1.2 | C3: -2 | D3: 2.9 | E3: 5 | F3: =+C3-B3 -> -0.8 | G3: =+E3-D3 -> 2.1 | I3: =-C3/E3 -> 0.4
A4: 18 | B4: -1.2 | C4: -2.6 | D4: 2 | E4: 3.8 | F4: =+C4-B4 -> -1.4 | G4: =+E4-D4 -> 1.8 | I4: =-C4/E4 -> 0.68421053
A5: 24 | B5: -1.3 | C5: -2.1 | D5: 1.9 | E5: 4.4 | F5: =+C5-B5 -> -0.8 | G5: =+E5-D5 -> 2.5 | I5: =-C5/E5 -> 0.47727273
A6: 30 | B6: -1.2 | C6: -2.4 | D6: 3.5 | E6: 5.9 | F6: =+C6-B6 -> -1.2 | G6: =+E6-D6 -> 2.4 | I6: =-C6/E6 -> 0.40677966
A7: 36 | B7: -1.1 | C7: -2.5 | D7: 4.5 | E7: 7 | F7: =+C7-B7 -> -1.4 | G7: =+E7-D7 -> 2.5 | I7: =-C7/E7 -> 0.35714286

Sheet Scenario Analysis
A1: MOB | B1: Risk Increase % | C1: Increased CoR (%) | D1: Decreased Net Profit (%) | E1: Net profit decrease (%) | F1: Used Auto Net Profit per Unit (Updated) | G1: Used Auto Net Profit per unit (current) | H1: # of Disb. Loans (before the risk increase) | I1: Increase (%) in # of Disb. Loans | J1: # of Disb. Loans (after the risk increase) | K1: Total Net Profit (before the risk increase) | L1: Total Net Profit (after the risk increase) | M1: Gain (€) | N1: Gain (%) | O1: Avg. Gain (%) | P1: Scenarios Increase (%) | Q1: Scenarios Increase (# of Appl.)
A2: 6 | B2: 10% | C2: =+'Summary (actuals)'!C2+('Summary (actuals)'!C2*'Scenario Analysis'!B2) -> -2.64 | D2: =+'Summary (actuals)'!E2-('Summary (actuals)'!C2-'Scenario Analysis'!C2) -> 4.06 | E2: =+D2-'Summary (actuals)'!E2 -> -0.24 | F2: =+Inputs!$B$2*('Scenario Analysis'!D2/100) -> 324.8 | G2: =+Inputs!$B$2*('Summary (actuals)'!E2/100) -> 344 | H2: 100 | I2: 0.0591 | J2: =+H2+(H2*I2) -> 105.91 | K2: =+H2*G2 -> 34400 | L2: =+J2*F2 -> 34399.568 | M2: =+L2-K2 -> -0.432 | N2: =+L2/K2-1 -> -1.255814e-05 | O2: =+SUM(L2:L7)/SUM(K2:K7)-1 -> -1.25e-06 | P2: production increase by c.5% break even point | Q2: =(-SUM(H2:H7)+SUM(J2:J7))/5 -> 6.0755105
A3: 12 | B3: 10% | C3: =+'Summary (actuals)'!C3+('Summary (actuals)'!C3*'Scenario Analysis'!B3) -> -2.2 | D3: =+'Summary (actuals)'!E3-('Summary (actuals)'!C3-'Scenario Analysis'!C3) -> 4.8 | E3: =+D3-'Summary (actuals)'!E3 -> -0.2 | F3: =+Inputs!$B$2*('Scenario Analysis'!D3/100) -> 384 | G3: =+Inputs!$B$2*('Summary (actuals)'!E3/100) -> 400 | H3: 100 | I3: 0.04167 | J3: =+H3+(H3*I3) -> 104.167 | K3: =+H3*G3 -> 40000 | L3: =+J3*F3 -> 40000.128 | M3: =+L3-K3 -> 0.128 | N3: =+L3/K3-1 -> 3.2e-06
A4: 18 | B4: 10% | C4: =+'Summary (actuals)'!C4+('Summary (actuals)'!C4*'Scenario Analysis'!B4) -> -2.86 | D4: =+'Summary (actuals)'!E4-('Summary (actuals)'!C4-'Scenario Analysis'!C4) -> 3.54 | E4: =+D4-'Summary (actuals)'!E4 -> -0.26 | F4: =+Inputs!$B$2*('Scenario Analysis'!D4/100) -> 283.2 | G4: =+Inputs!$B$2*('Summary (actuals)'!E4/100) -> 304 | H4: 100 | I4: 0.073446328 | J4: =+H4+(H4*I4) -> 107.34463 | K4: =+H4*G4 -> 30400 | L4: =+J4*F4 -> 30400 | M4: =+L4-K4 -> 0 | N4: =+L4/K4-1 -> 0
A5: 24 | B5: 10% | C5: =+'Summary (actuals)'!C5+('Summary (actuals)'!C5*'Scenario Analysis'!B5) -> -2.31 | D5: =+'Summary (actuals)'!E5-('Summary (actuals)'!C5-'Scenario Analysis'!C5) -> 4.19 | E5: =+D5-'Summary (actuals)'!E5 -> -0.21 | F5: =+Inputs!$B$2*('Scenario Analysis'!D5/100) -> 335.2 | G5: =+Inputs!$B$2*('Summary (actuals)'!E5/100) -> 352 | H5: 100 | I5: 0.050119332 | J5: =+H5+(H5*I5) -> 105.01193 | K5: =+H5*G5 -> 35200 | L5: =+J5*F5 -> 35200 | M5: =+L5-K5 -> 0 | N5: =+L5/K5-1 -> 0
A6: 30 | B6: 10% | C6: =+'Summary (actuals)'!C6+('Summary (actuals)'!C6*'Scenario Analysis'!B6) -> -2.64 | D6: =+'Summary (actuals)'!E6-('Summary (actuals)'!C6-'Scenario Analysis'!C6) -> 5.66 | E6: =+D6-'Summary (actuals)'!E6 -> -0.24 | F6: =+Inputs!$B$2*('Scenario Analysis'!D6/100) -> 452.8 | G6: =+Inputs!$B$2*('Summary (actuals)'!E6/100) -> 472 | H6: 100 | I6: 0.042402827 | J6: =+H6+(H6*I6) -> 104.24028 | K6: =+H6*G6 -> 47200 | L6: =+J6*F6 -> 47200 | M6: =+L6-K6 -> 0 | N6: =+L6/K6-1 -> 0
A7: 36 | B7: 10% | C7: =+'Summary (actuals)'!C7+('Summary (actuals)'!C7*'Scenario Analysis'!B7) -> -2.75 | D7: =+'Summary (actuals)'!E7-('Summary (actuals)'!C7-'Scenario Analysis'!C7) -> 6.75 | E7: =+D7-'Summary (actuals)'!E7 -> -0.25 | F7: =+Inputs!$B$2*('Scenario Analysis'!D7/100) -> 540 | G7: =+Inputs!$B$2*('Summary (actuals)'!E7/100) -> 560 | H7: 100 | I7: 0.037037037 | J7: =+H7+(H7*I7) -> 103.7037 | K7: =+H7*G7 -> 56000 | L7: =+J7*F7 -> 56000 | M7: =+L7-K7 -> 0 | N7: =+L7/K7-1 -> 0
A8: 6 | B8: =+B2 -> 10% | C8: =+'Summary (actuals)'!C2+('Summary (actuals)'!C2*'Scenario Analysis'!B8) -> -2.64 | D8: =+'Summary (actuals)'!E2-('Summary (actuals)'!C2-'Scenario Analysis'!C8) -> 4.06 | E8: =+D8-'Summary (actuals)'!E2 -> -0.24 | F8: =+Inputs!$B$2*('Scenario Analysis'!D8/100) -> 324.8 | G8: =+Inputs!$B$2*('Summary (actuals)'!E2/100) -> 344 | H8: 100 | I8: 0.1 | J8: =+H8+(H8*I8) -> 110 | K8: =+H8*G8 -> 34400 | L8: =+J8*F8 -> 35728 | M8: =+L8-K8 -> 1328 | N8: =+L8/K8-1 -> 0.038604651 | O8: =+SUM(L8:L13)/SUM(K8:K13)-1 -> 0.049342105 | P8: production increase by 10% | Q8: =(-SUM(H2:H7)+SUM(J8:J13))/5 -> 12
A9: 12 | B9: =+B3 -> 10% | C9: =+'Summary (actuals)'!C3+('Summary (actuals)'!C3*'Scenario Analysis'!B9) -> -2.2 | D9: =+'Summary (actuals)'!E3-('Summary (actuals)'!C3-'Scenario Analysis'!C9) -> 4.8 | E9: =+D9-'Summary (actuals)'!E3 -> -0.2 | F9: =+Inputs!$B$2*('Scenario Analysis'!D9/100) -> 384 | G9: =+Inputs!$B$2*('Summary (actuals)'!E3/100) -> 400 | H9: 100 | I9: =+I8 -> 0.1 | J9: =+H9+(H9*I9) -> 110 | K9: =+H9*G9 -> 40000 | L9: =+J9*F9 -> 42240 | M9: =+L9-K9 -> 2240 | N9: =+L9/K9-1 -> 0.056
A10: 18 | B10: =+B4 -> 10% | C10: =+'Summary (actuals)'!C4+('Summary (actuals)'!C4*'Scenario Analysis'!B10) -> -2.86 | D10: =+'Summary (actuals)'!E4-('Summary (actuals)'!C4-'Scenario Analysis'!C10) -> 3.54 | E10: =+D10-'Summary (actuals)'!E4 -> -0.26 | F10: =+Inputs!$B$2*('Scenario Analysis'!D10/100) -> 283.2 | G10: =+Inputs!$B$2*('Summary (actuals)'!E4/100) -> 304 | H10: 100 | I10: =+I9 -> 0.1 | J10: =+H10+(H10*I10) -> 110 | K10: =+H10*G10 -> 30400 | L10: =+J10*F10 -> 31152 | M10: =+L10-K10 -> 752 | N10: =+L10/K10-1 -> 0.024736842
A11: 24 | B11: =+B5 -> 10% | C11: =+'Summary (actuals)'!C5+('Summary (actuals)'!C5*'Scenario Analysis'!B11) -> -2.31 | D11: =+'Summary (actuals)'!E5-('Summary (actuals)'!C5-'Scenario Analysis'!C11) -> 4.19 | E11: =+D11-'Summary (actuals)'!E5 -> -0.21 | F11: =+Inputs!$B$2*('Scenario Analysis'!D11/100) -> 335.2 | G11: =+Inputs!$B$2*('Summary (actuals)'!E5/100) -> 352 | H11: 100 | I11: =+I10 -> 0.1 | J11: =+H11+(H11*I11) -> 110 | K11: =+H11*G11 -> 35200 | L11: =+J11*F11 -> 36872 | M11: =+L11-K11 -> 1672 | N11: =+L11/K11-1 -> 0.0475
A12: 30 | B12: =+B6 -> 10% | C12: =+'Summary (actuals)'!C6+('Summary (actuals)'!C6*'Scenario Analysis'!B12) -> -2.64 | D12: =+'Summary (actuals)'!E6-('Summary (actuals)'!C6-'Scenario Analysis'!C12) -> 5.66 | E12: =+D12-'Summary (actuals)'!E6 -> -0.24 | F12: =+Inputs!$B$2*('Scenario Analysis'!D12/100) -> 452.8 | G12: =+Inputs!$B$2*('Summary (actuals)'!E6/100) -> 472 | H12: 100 | I12: =+I11 -> 0.1 | J12: =+H12+(H12*I12) -> 110 | K12: =+H12*G12 -> 47200 | L12: =+J12*F12 -> 49808 | M12: =+L12-K12 -> 2608 | N12: =+L12/K12-1 -> 0.055254237
A13: 36 | B13: =+B7 -> 10% | C13: =+'Summary (actuals)'!C7+('Summary (actuals)'!C7*'Scenario Analysis'!B13) -> -2.75 | D13: =+'Summary (actuals)'!E7-('Summary (actuals)'!C7-'Scenario Analysis'!C13) -> 6.75 | E13: =+D13-'Summary (actuals)'!E7 -> -0.25 | F13: =+Inputs!$B$2*('Scenario Analysis'!D13/100) -> 540 | G13: =+Inputs!$B$2*('Summary (actuals)'!E7/100) -> 560 | H13: 100 | I13: =+I12 -> 0.1 | J13: =+H13+(H13*I13) -> 110 | K13: =+H13*G13 -> 56000 | L13: =+J13*F13 -> 59400 | M13: =+L13-K13 -> 3400 | N13: =+L13/K13-1 -> 0.060714286
A14: 6 | B14: 0.1 | C14: =+'Summary (actuals)'!C2+('Summary (actuals)'!C2*'Scenario Analysis'!B14) -> -2.64 | D14: =+'Summary (actuals)'!E2-('Summary (actuals)'!C2-'Scenario Analysis'!C14) -> 4.06 | E14: =+D14-'Summary (actuals)'!E2 -> -0.24 | F14: =+Inputs!$B$2*('Scenario Analysis'!D14/100) -> 324.8 | G14: =+G2 -> 344 | H14: 100 | I14: 0.15 | J14: =+H14+(H14*I14) -> 115 | K14: =+H14*G14 -> 34400 | L14: =+J14*F14 -> 37352 | M14: =+L14-K14 -> 2952 | N14: =+L14/K14-1 -> 0.085813953 | O14: =+SUM(L14:L19)/SUM(K14:K19)-1 -> 0.097039474 | P14: production increase by 15% | Q14: =(-SUM(H2:H7)+SUM(J14:J19))/5 -> 18
A15: 12 | B15: 0.1 | C15: =+'Summary (actuals)'!C3+('Summary (actuals)'!C3*'Scenario Analysis'!B15) -> -2.2 | D15: =+'Summary (actuals)'!E3-('Summary (actuals)'!C3-'Scenario Analysis'!C15) -> 4.8 | E15: =+D15-'Summary (actuals)'!E3 -> -0.2 | F15: =+Inputs!$B$2*('Scenario Analysis'!D15/100) -> 384 | G15: =+G3 -> 400 | H15: 100 | I15: =+I14 -> 0.15 | J15: =+H15+(H15*I15) -> 115 | K15: =+H15*G15 -> 40000 | L15: =+J15*F15 -> 44160 | M15: =+L15-K15 -> 4160 | N15: =+L15/K15-1 -> 0.104
A16: 18 | B16: 0.1 | C16: =+'Summary (actuals)'!C4+('Summary (actuals)'!C4*'Scenario Analysis'!B16) -> -2.86 | D16: =+'Summary (actuals)'!E4-('Summary (actuals)'!C4-'Scenario Analysis'!C16) -> 3.54 | E16: =+D16-'Summary (actuals)'!E4 -> -0.26 | F16: =+Inputs!$B$2*('Scenario Analysis'!D16/100) -> 283.2 | G16: =+G4 -> 304 | H16: 100 | I16: =+I15 -> 0.15 | J16: =+H16+(H16*I16) -> 115 | K16: =+H16*G16 -> 30400 | L16: =+J16*F16 -> 32568 | M16: =+L16-K16 -> 2168 | N16: =+L16/K16-1 -> 0.071315789
A17: 24 | B17: 0.1 | C17: =+'Summary (actuals)'!C5+('Summary (actuals)'!C5*'Scenario Analysis'!B17) -> -2.31 | D17: =+'Summary (actuals)'!E5-('Summary (actuals)'!C5-'Scenario Analysis'!C17) -> 4.19 | E17: =+D17-'Summary (actuals)'!E5 -> -0.21 | F17: =+Inputs!$B$2*('Scenario Analysis'!D17/100) -> 335.2 | G17: =+G5 -> 352 | H17: 100 | I17: =+I16 -> 0.15 | J17: =+H17+(H17*I17) -> 115 | K17: =+H17*G17 -> 35200 | L17: =+J17*F17 -> 38548 | M17: =+L17-K17 -> 3348 | N17: =+L17/K17-1 -> 0.095113636
A18: 30 | B18: 0.1 | C18: =+'Summary (actuals)'!C6+('Summary (actuals)'!C6*'Scenario Analysis'!B18) -> -2.64 | D18: =+'Summary (actuals)'!E6-('Summary (actuals)'!C6-'Scenario Analysis'!C18) -> 5.66 | E18: =+D18-'Summary (actuals)'!E6 -> -0.24 | F18: =+Inputs!$B$2*('Scenario Analysis'!D18/100) -> 452.8 | G18: =+G6 -> 472 | H18: 100 | I18: =+I17 -> 0.15 | J18: =+H18+(H18*I18) -> 115 | K18: =+H18*G18 -> 47200 | L18: =+J18*F18 -> 52072 | M18: =+L18-K18 -> 4872 | N18: =+L18/K18-1 -> 0.10322034
A19: 36 | B19: 0.1 | C19: =+'Summary (actuals)'!C7+('Summary (actuals)'!C7*'Scenario Analysis'!B19) -> -2.75 | D19: =+'Summary (actuals)'!E7-('Summary (actuals)'!C7-'Scenario Analysis'!C19) -> 6.75 | E19: =+D19-'Summary (actuals)'!E7 -> -0.25 | F19: =+Inputs!$B$2*('Scenario Analysis'!D19/100) -> 540 | G19: =+G7 -> 560 | H19: 100 | I19: =+I18 -> 0.15 | J19: =+H19+(H19*I19) -> 115 | K19: =+H19*G19 -> 56000 | L19: =+J19*F19 -> 62100 | M19: =+L19-K19 -> 6100 | N19: =+L19/K19-1 -> 0.10892857
A20: 6 | B20: 0.1 | C20: =+'Summary (actuals)'!C2+('Summary (actuals)'!C2*'Scenario Analysis'!B20) -> -2.64 | D20: =+'Summary (actuals)'!E2-('Summary (actuals)'!C2-'Scenario Analysis'!C20) -> 4.06 | E20: =+D14-'Summary (actuals)'!E2 -> -0.24 | F20: =+Inputs!$B$2*('Scenario Analysis'!D20/100) -> 324.8 | G20: =+G2 -> 344 | H20: 100 | I20: 0.2 | J20: =+H20+(H20*I20) -> 120 | K20: =+H20*G20 -> 34400 | L20: =+J20*F20 -> 38976 | M20: =+L20-K20 -> 4576 | N20: =+L20/K20-1 -> 0.13302326 | O20: =+SUM(L20:L25)/SUM(K20:K25)-1 -> 0.14473684 | P20: production increase by 20% | Q20: =(-SUM(H2:H7)+SUM(J20:J25))/5 -> 24
A21: 12 | B21: 0.1 | C21: =+'Summary (actuals)'!C3+('Summary (actuals)'!C3*'Scenario Analysis'!B21) -> -2.2 | D21: =+'Summary (actuals)'!E3-('Summary (actuals)'!C3-'Scenario Analysis'!C21) -> 4.8 | E21: =+D15-'Summary (actuals)'!E3 -> -0.2 | F21: =+Inputs!$B$2*('Scenario Analysis'!D21/100) -> 384 | G21: =+G3 -> 400 | H21: 100 | I21: =+I20 -> 0.2 | J21: =+H21+(H21*I21) -> 120 | K21: =+H21*G21 -> 40000 | L21: =+J21*F21 -> 46080 | M21: =+L21-K21 -> 6080 | N21: =+L21/K21-1 -> 0.152
A22: 18 | B22: 0.1 | C22: =+'Summary (actuals)'!C4+('Summary (actuals)'!C4*'Scenario Analysis'!B22) -> -2.86 | D22: =+'Summary (actuals)'!E4-('Summary (actuals)'!C4-'Scenario Analysis'!C22) -> 3.54 | E22: =+D16-'Summary (actuals)'!E4 -> -0.26 | F22: =+Inputs!$B$2*('Scenario Analysis'!D22/100) -> 283.2 | G22: =+G4 -> 304 | H22: 100 | I22: =+I21 -> 0.2 | J22: =+H22+(H22*I22) -> 120 | K22: =+H22*G22 -> 30400 | L22: =+J22*F22 -> 33984 | M22: =+L22-K22 -> 3584 | N22: =+L22/K22-1 -> 0.11789474
A23: 24 | B23: 0.1 | C23: =+'Summary (actuals)'!C5+('Summary (actuals)'!C5*'Scenario Analysis'!B23) -> -2.31 | D23: =+'Summary (actuals)'!E5-('Summary (actuals)'!C5-'Scenario Analysis'!C23) -> 4.19 | E23: =+D17-'Summary (actuals)'!E5 -> -0.21 | F23: =+Inputs!$B$2*('Scenario Analysis'!D23/100) -> 335.2 | G23: =+G5 -> 352 | H23: 100 | I23: =+I22 -> 0.2 | J23: =+H23+(H23*I23) -> 120 | K23: =+H23*G23 -> 35200 | L23: =+J23*F23 -> 40224 | M23: =+L23-K23 -> 5024 | N23: =+L23/K23-1 -> 0.14272727
A24: 30 | B24: 0.1 | C24: =+'Summary (actuals)'!C6+('Summary (actuals)'!C6*'Scenario Analysis'!B24) -> -2.64 | D24: =+'Summary (actuals)'!E6-('Summary (actuals)'!C6-'Scenario Analysis'!C24) -> 5.66 | E24: =+D18-'Summary (actuals)'!E6 -> -0.24 | F24: =+Inputs!$B$2*('Scenario Analysis'!D24/100) -> 452.8 | G24: =+G6 -> 472 | H24: 100 | I24: =+I23 -> 0.2 | J24: =+H24+(H24*I24) -> 120 | K24: =+H24*G24 -> 47200 | L24: =+J24*F24 -> 54336 | M24: =+L24-K24 -> 7136 | N24: =+L24/K24-1 -> 0.15118644
A25: 36 | B25: 0.1 | C25: =+'Summary (actuals)'!C7+('Summary (actuals)'!C7*'Scenario Analysis'!B25) -> -2.75 | D25: =+'Summary (actuals)'!E7-('Summary (actuals)'!C7-'Scenario Analysis'!C25) -> 6.75 | E25: =+D19-'Summary (actuals)'!E7 -> -0.25 | F25: =+Inputs!$B$2*('Scenario Analysis'!D25/100) -> 540 | G25: =+G7 -> 560 | H25: 100 | I25: =+I24 -> 0.2 | J25: =+H25+(H25*I25) -> 120 | K25: =+H25*G25 -> 56000 | L25: =+J25*F25 -> 64800 | M25: =+L25-K25 -> 8800 | N25: =+L25/K25-1 -> 0.15714286
